Workbook

Sheet ANALYSIS
A1: Summary Info
B2: Name of the Account Holder | C2: AFFAN METALS
B3: Address | C3: XXXXXXXXXXXXXXXXXXXXXXXXXXXXXXXXXXXXXXXXXXXXXXXXXXXXXXXXXXXXXXXXXXXXXXXXX
B4: Email
B5: PAN
B6: Mobile Number
B7: Name of the Bank | C7: Tamilnad Mercantile Bank Ltd., India
B8: Account Number | C8: XXXXXXXXXX75048
B9: Account Type | C9: Current Account
A11: Monthwise Details
C12: Aug-25 | D12: Sep-25 | E12: Oct-25 | F12: Nov-25 | G12: Dec-25 | H12: Jan-26 | I12: TOTAL
B13: Total No. of Credit Transactions | C13: 71 | D13: 89 | E13: 43 | F13: 54 | G13: 48 | H13: 26 | I13: =SUM(B13:H13) -> 331
B14: Total Amount of Credit Transactions | C14: 47724778 | D14: 45540611 | E14: 32281912 | F14: 42903931 | G14: 38198233 | H14: 18006852 | I14: =SUM(B14:H14) -> 2.2465632e+08
B15: Total No. of Debit Transactions | C15: 65 | D15: 76 | E15: 56 | F15: 76 | G15: 67 | H15: 44 | I15: =SUM(B15:H15) -> 384
B16: Total Amount of Debit Transactions | C16: 46403257 | D16: 46380731 | E16: 32519360 | F16: 42611297 | G16: 35674195 | H16: 20153318 | I16: =SUM(B16:H16) -> 2.2374216e+08
B17: Total No. of Cash Deposits | C17: 0 | D17: 0 | E17: 0 | F17: 2 | G17: 1 | H17: 0 | I17: =SUM(B17:H17) -> 3
B18: Total Amount of Cash Deposits | C18: 0 | D18: 0 | E18: 0 | F18: 1700000 | G18: 700000 | H18: 0 | I18: =SUM(B18:H18) -> 2400000
B19: Total No. of Cash Withdrawals | C19: 3 | D19: 4 | E19: 1 | F19: 4 | G19: 3 | H19: 0 | I19: =SUM(B19:H19) -> 15
B20: Total Amount of Cash Withdrawals | C20: 225000 | D20: 650000 | E20: 50000 | F20: 580000 | G20: 450000 | H20: 0 | I20: =SUM(B20:H20) -> 1955000
B21: Total No. of Cheque Deposits | C21: 0 | D21: 0 | E21: 0 | F21: 0 | G21: 0 | H21: 0 | I21: =SUM(B21:H21) -> 0
B22: Total Amount of Cheque Deposits | C22: 0 | D22: 0 | E22: 0 | F22: 0 | G22: 0 | H22: 0 | I22: =SUM(B22:H22) -> 0
B23: Total No. of Cheque Issues | C23: 0 | D23: 0 | E23: 0 | F23: 0 | G23: 0 | H23: 0 | I23: =SUM(B23:H23) -> 0
B24: Total Amount of Cheque Issues | C24: 0 | D24: 0 | E24: 0 | F24: 0 | G24: 0 | H24: 0 | I24: =SUM(B24:H24) -> 0
... B33: Monthwise Peak delay of overdrawing days | C33: 0 | D33: 0 | E33: 0 | F33: 0 | G33: 0 | H33: 0 | I33: =SUM(B33:H33) -> 0
B34: Inward Cheque Return (%) | C34: =IF(C23 > 0, C25 / C23, 0) -> 0 | D34: =IF(D23 > 0, D25 / D23, 0) -> 0 | E34: =IF(E23 > 0, E25 / E23, 0) -> 0 | F34: =IF(F23 > 0, F25 / F23, 0) -> 0 | G34: =IF(G23 > 0, G25 / G23, 0) -> 0 | H34: =IF(H23 > 0, H25 / H23, 0) -> 0 | I34: =SUM(B34:H34) -> 0
B35: Outward Cheque Return (%) | C35: =IF(C21 > 0, C26 / C21, 0) -> 0 | D35: =IF(D21 > 0, D26 / D21, 0) -> 0 | E35: =IF(E21 > 0, E26 / E21, 0) -> 0 | F35: =IF(F21 > 0, F26 / F21, 0) -> 0 | G35: =IF(G21 > 0, G26 / G21, 0) -> 0 | H35: =IF(H21 > 0, H26 / H21, 0) -> 0 | I35: =SUM(B35:H35) -> 0
B36: Overdrawn Instances No. of days | C36: 0 | D36: 0 | E36: 0 | F36: 0 | G36: 0 | H36: 0 | I36: =SUM(B36:H36) -> 0
B37: Overdrawn Amount(for all days) | C37: 0 | D37: 0 | E37: 0 | F37: 0 | G37: 0 | H37: 0 | I37: =SUM(B37:H37) -> 0
B38: Overdrawn Average Amount | C38: =IF(0 > 0, C37 / 0, 0) -> 0 | D38: =IF(0 > 0, D37 / 0, 0) -> 0 | E38: =IF(0 > 0, E37 / 0, 0) -> 0 | F38: =IF(0 > 0, F37 / 0, 0) -> 0 | G38: =IF(0 > 0, G37 / 0, 0) -> 0 | H38: =IF(0 > 0, H37 / 0, 0) -> 0 | I38: =SUM(B38:H38) -> 0
B39: Overdrawn Average as % of Limit | C39: =IF(0 > 0, C38 / C28, 0) -> 0 | D39: =IF(0 > 0, D38 / D28, 0) -> 0 | E39: =IF(0 > 0, E38 / E28, 0) -> 0 | F39: =IF(0 > 0, F38 / F28, 0) -> 0 | G39: =IF(0 > 0, G38 / G28, 0) -> 0 | H39: =IF(0 > 0, H38 / H28, 0) -> 0 | I39: =SUM(B39:H39) -> 0
B40: Total Delay in Interest Payment (in days) | C40: 0 | D40: 0 | E40: 0 | F40: 0 | G40: 0 | H40: 0 | I40: =SUM(B40:H40) -> 0
B41: Penal Interest > Rs. 500/- No. of times | C41: 0 | D41: 0 | E41: 0 | F41: 0 | G41: 0 | H41: 0 | I41: =SUM(B41:H41) -> 0
B42: No of Tranfers from Own Accounts | C42: 0 | D42: 0 | E42: 0 | F42: 0 | G42: 0 | H42: 0 | I42: =SUM(B42:H42) -> 0
B43: Value of Transfer from Own Accounts (Rs. lakhs) | C43: 0 | D43: 0 | E43: 0 | F43: 0 | G43: 0 | H43: 0 | I43: =SUM(B43:H43) -> 0
B44: Balance on 5th | C44: 71089.01 | D44: 219458.01 | E44: 869387.4 | F44: 53901.04 | G44: 1395659.3 | H44: 468994.32 | I44: =SUM(B44:H44) -> 3078489.1
B45: Balance on 15th | C45: 727288.01 | D45: 307123.94 | E45: 532877.43 | F45: 688364.86 | G45: 3211803.3 | H45: 1262130 | I45: =SUM(B45:H45) -> 6729587.6
B46: Balance on 25th | C46: 782889.01 | D46: 3109252.4 | E46: 905204.43 | F46: 95317.32 | G46: 1010731.3 | H46: 970065.48 | I46: =SUM(B46:H46) -> 6873460
B47: Min EOD Balance | C47: 32928.55 | D47: 81049.94 | E47: 32877.43 | F47: 17572.04 | G47: 10731.32 | H47: 68994.32
B48: Max EOD Balance | C48: 3246871 | D48: 5287975.4 | E48: 1049859 | F48: 4127631 | G48: 4736326.3 | H48: 3198974.3
B49: Average EOD Balance | C49: 747336.37 | D49: 1922632.5 | E49: 456031.94 | F49: 731420.41 | G49: 840215.09 | H49: 1142287.8
B52: File Name | C52: Institution | D52: Account No | E52: Transaction Start Date | F52: Transaction End Date | G52: Name as in Statement | H52: Address as in Statement | I52: Mobile as in Statement | J52: Landline as in Statement | K52: Email as in Statement | L52: PAN as in Statement | M52: Password Protected | N52: Statement Status | O52: Perfios Transaction Id
B53: AffanTMBCAAug2025toJan2026190126.pdf | C53: Tamilnad Mercantile Bank Ltd., India | D53: XXXXXXXXXXX5048 | E53: 45870 | F53: 46041 | G53: AFFAN METALS | M53: No | N53: VERIFIED | O53: 99ZN1770283626523
A62: Summary Info
B63: Name of the Account Holder | C63: VEERA INDUSTRIES
B64: Address | C64: XXXXXXXXXXXXXXXXXXXXXXXXXXXXXXXXXXXXXXXXXXXXXXXXXXXXXXXXXXXXXXXXXXXXXXXXXXXXXXXXXXXXXXXXXXXXXX
B65: Email
B66: PAN
B67: Mobile Number
B68: Name of the Bank | C68: Tamilnad Mercantile Bank Ltd., India
B69: Account Number | C69: XXXXXXXXXX00123
B70: Account Type | C70: Cash Credit Account
A72: Monthwise Details
C73: Aug-25 | D73: Sep-25 | E73: Oct-25 | F73: Nov-25 | G73: Dec-25 | H73: Jan-26 | I73: TOTAL
B74: Total No. of Credit Transactions | C74: 21 | D74: 21 | E74: 11 | F74: 25 | G74: 14 | H74: 11 | I74: =SUM(B74:H74) -> 103
B75: Total Amount of Credit Transactions | C75: 45756790 | D75: 21423074 | E75: 8233617.4 | F75: 20677540 | G75: 12560001 | H75: 23325767 | I75: =SUM(B75:H75) -> 1.3197679e+08
B76: Total No. of Debit Transactions | C76: 59 | D76: 47 | E76: 42 | F76: 54 | G76: 42 | H76: 31 | I76: =SUM(B76:H76) -> 275
B77: Total Amount of Debit Transactions | C77: 45835161 | D77: 21063884 | E77: 6558010.5 | F77: 22691695 | G77: 12571190 | H77: 22975175 | I77: =SUM(B77:H77) -> 1.3169512e+08
B78: Total No. of Cash Deposits | C78: 0 | D78: 0 | E78: 0 | F78: 1 | G78: 1 | H78: 0 | I78: =SUM(B78:H78) -> 2
B79: Total Amount of Cash Deposits | C79: 0 | D79: 0 | E79: 0 | F79: 500000 | G79: 350000 | H79: 0 | I79: =SUM(B79:H79) -> 850000
B80: Total No. of Cash Withdrawals | C80: 2 | D80: 3 | E80: 2 | F80: 2 | G80: 5 | H80: 0 | I80: =SUM(B80:H80) -> 14
B81: Total Amount of Cash Withdrawals | C81: 200000 | D81: 400000 | E81: 250000 | F81: 150000 | G81: 550000 | H81: 0 | I81: =SUM(B81:H81) -> 1550000
B82: Total No. of Cheque Deposits | C82: 0 | D82: 0 | E82: 0 | F82: 0 | G82: 0 | H82: 0 | I82: =SUM(B82:H82) -> 0
B83: Total Amount of Cheque Deposits | C83: 0 | D83: 0 | E83: 0 | F83: 0 | G83: 0 | H83: 0 | I83: =SUM(B83:H83) -> 0
B84: Total No. of Cheque Issues | C84: 0 | D84: 0 | E84: 0 | F84: 0 | G84: 0 | H84: 0 | I84: =SUM(B84:H84) -> 0
B85: Total Amount of Cheque Issues | C85: 0 | D85: 0 | E85: 0 | F85: 0 | G85: 0 | H85: 0 | I85: =SUM(B85:H85) -> 0
... B94: Monthwise Peak delay of overdrawing days | C94: 0 | D94: 0 | E94: 0 | F94: 0 | G94: 0 | H94: 0 | I94: =SUM(B94:H94) -> 0
B95: Inward Cheque Return (%) | C95: =IF(C84 > 0, C86 / C84, 0) -> 0 | D95: =IF(D84 > 0, D86 / D84, 0) -> 0 | E95: =IF(E84 > 0, E86 / E84, 0) -> 0 | F95: =IF(F84 > 0, F86 / F84, 0) -> 0 | G95: =IF(G84 > 0, G86 / G84, 0) -> 0 | H95: =IF(H84 > 0, H86 / H84, 0) -> 0 | I95: =SUM(B95:H95) -> 0
B96: Outward Cheque Return (%) | C96: =IF(C82 > 0, C87 / C82, 0) -> 0 | D96: =IF(D82 > 0, D87 / D82, 0) -> 0 | E96: =IF(E82 > 0, E87 / E82, 0) -> 0 | F96: =IF(F82 > 0, F87 / F82, 0) -> 0 | G96: =IF(G82 > 0, G87 / G82, 0) -> 0 | H96: =IF(H82 > 0, H87 / H82, 0) -> 0 | I96: =SUM(B96:H96) -> 0
B97: Overdrawn Instances No. of days | C97: 0 | D97: 0 | E97: 0 | F97: 0 | G97: 0 | H97: 0 | I97: =SUM(B97:H97) -> 0
B98: Overdrawn Amount(for all days) | C98: 0 | D98: 0 | E98: 0 | F98: 0 | G98: 0 | H98: 0 | I98: =SUM(B98:H98) -> 0
B99: Overdrawn Average Amount | C99: =IF(0 > 0, C98 / 0, 0) -> 0 | D99: =IF(0 > 0, D98 / 0, 0) -> 0 | E99: =IF(0 > 0, E98 / 0, 0) -> 0 | F99: =IF(0 > 0, F98 / 0, 0) -> 0 | G99: =IF(0 > 0, G98 / 0, 0) -> 0 | H99: =IF(0 > 0, H98 / 0, 0) -> 0 | I99: =SUM(B99:H99) -> 0
B100: Overdrawn Average as % of Limit | C100: =IF(0 > 0, C99 / C89, 0) -> 0 | D100: =IF(0 > 0, D99 / D89, 0) -> 0 | E100: =IF(0 > 0, E99 / E89, 0) -> 0 | F100: =IF(0 > 0, F99 / F89, 0) -> 0 | G100: =IF(0 > 0, G99 / G89, 0) -> 0 | H100: =IF(0 > 0, H99 / H89, 0) -> 0 | I100: =SUM(B100:H100) -> 0
B101: Total Delay in Interest Payment (in days) | C101: 2 | D101: 2 | E101: 3 | F101: 4 | G101: 3 | H101: 0 | I101: =SUM(B101:H101) -> 14
B102: Penal Interest > Rs. 500/- No. of times | C102: 2 | D102: 0 | E102: 1 | F102: 1 | G102: 2 | H102: 0 | I102: =SUM(B102:H102) -> 6
B103: No of Tranfers from Own Accounts | C103: 0 | D103: 0 | E103: 2 | F103: 0 | G103: 0 | H103: 0 | I103: =SUM(B103:H103) -> 2
B104: Value of Transfer from Own Accounts (Rs. lakhs) | C104: 0 | D104: 0 | E104: 0.0006138 | F104: 0 | G104: 0 | H104: 0 | I104: =SUM(B104:H104) -> 0.0006138
B105: Balance on 5th | C105: -39923452 | D105: -39799365 | E105: -39738318 | F105: -39967284 | G105: -39262003 | H105: -39976056 | I105: =SUM(B105:H105) -> -2.3866648e+08
B106: Balance on 15th | C106: -38751677 | D106: -39965621 | E106: -39979818 | F106: -38095683 | G106: -39782268 | H106: -39970463 | I106: =SUM(B106:H106) -> -2.3654553e+08
B107: Balance on 25th | C107: -39967817 | D107: -39760205 | E107: -39714353 | F107: -39952595 | G107: -39942193 | H107: -39975463 | I107: =SUM(B107:H107) -> -2.3931262e+08
B108: Min EOD Balance | C108: -40335508 | D108: -40335508 | E108: -39990122 | F108: -40314867 | G108: -40326056 | H108: -40326056
B109: Max EOD Balance | C109: -29860225 | D109: -38660205 | E109: -38121034 | F109: -38015683 | G109: -37328367 | H109: -34841717
B110: Average EOD Balance | C110: -38913128 | D110: -39701710 | E110: -39735930 | F110: -39705345 | G110: -39815333 | H110: -39029939
B113: File Name | C113: Institution | D113: Account No | E113: Transaction Start Date | F113: Transaction End Date | G113: Name as in Statement | H113: Address as in Statement | I113: Mobile as in Statement | J113: Landline as in Statement | K113: Email as in Statement | L113: PAN as in Statement | M113: Password Protected | N113: Statement Status | O113: Perfios Transaction Id
B114: VeeraTMBCCAug2025toJan2026190126.pdf | C114: Tamilnad Mercantile Bank Ltd., India | D114: XXXXXXXXXX00123 | E114: 45870 | F114: 46041 | G114: VEERA INDUSTRIES | M114: No | N114: VERIFIED | O114: 4Y3H1770283607699

Sheet ODD FIG
C1: TMB-5048-CA
A2: Date | B2: MONTH | C2: TYPE | D2: Cheque_No | E2: Category | F2: DR | G2: CR
A3: 45899 | B3: AUG | C3: ODD FIG | E3: LATHA | G3: 1200000
A4: 45917 | B4: SEP | C4: ODD FIG | E4: LATHA | G4: 780000
A5: 45877 | B5: AUG | C5: ODD FIG | E5: NATARAJAN M | G5: 1000000
A6: 45895 | B6: AUG | C6: ODD FIG | E6: NATARAJAN M | G6: 750000
A7: 45899 | B7: AUG | C7: ODD FIG | E7: NATARAJAN M | G7: 800000
A8: 46003 | B8: DEC | C8: ODD FIG | E8: NATARAJAN M | G8: 400000
A9: 45874 | B9: AUG | C9: ODD FIG | E9: SRINIVAS K R | G9: 1
A10: 45874 | B10: AUG | C10: ODD FIG | E10: SRINIVAS K R | G10: 2500000
A11: 45906 | B11: SEP | C11: ODD FIG | E11: SRINIVAS K R | G11: 1400000
A12: 45908 | B12: SEP | C12: ODD FIG | E12: SRINIVAS K R | G12: 1000000
A13: 45909 | B13: SEP | C13: ODD FIG | E13: SRINIVAS K R | G13: 1100000
A14: 45909 | B14: SEP | C14: ODD FIG | E14: SRINIVAS K R | G14: 300000
... A28: 45895 | B28: AUG | C28: ODD FIG | E28: VENKATESAN | G28: 500000

Sheet DOUBT
C1: TMB-5048-CA
A2: Date | B2: MONTH | C2: TYPE | D2: Cheque_No | E2: Category | F2: DR | G2: CR
A3: 46035 | B3: JAN(26) | C3: DOUBT | E3: BUILDING APPROVAL | F3: 1010500
A4: 46005 | B4: DEC | C4: DOUBT | E4: ITDTAX REFUND | G4: 3421590
A5: 46023 | B5: JAN(26) | C5: DOUBT | E5: ITDTAX REFUND | G5: 82443
C17: TMB-0123-OD
A18: Date | B18: MONTH | C18: TYPE | D18: Cheque_No | E18: Category | F18: DR | G18: CR
A19: 45870 | B19: AUG | C19: DOUBT | E19: Bill Id | G19: 1910980
A20: 45870 | B20: AUG | C20: DOUBT | E20: Bill Id | F20: 30047.5
A21: 45883 | B21: AUG | C21: DOUBT | E21: Bill Id | G21: 1121543
A22: 45883 | B22: AUG | C22: DOUBT | E22: Bill Id | F22: 17298.5
A23: 45894 | B23: AUG | C23: DOUBT | E23: Bill Id | F23: 277.3
A24: 45910 | B24: SEP | C24: DOUBT | E24: Bill Id | G24: 321715
A25: 45910 | B25: SEP | C25: DOUBT | E25: Bill Id | G25: 727765
A26: 45910 | B26: SEP | C26: DOUBT | E26: Bill Id | F26: 4256.42
A27: 45910 | B27: SEP | C27: DOUBT | E27: Bill Id | F27: 9051.5
A28: 45943 | B28: OCT | C28: DOUBT | E28: Bill Id | G28: 1826569
A29: 45943 | B29: OCT | C29: DOUBT | E29: Bill Id | F29: 25205.5
A30: 45961 | B30: OCT | C30: DOUBT | E30: Bill Id | G30: 2026987
A31: 45961 | B31: OCT | C31: DOUBT | E31: Bill Id | F31: 32022.5
A32: 45973 | B32: NOV | C32: DOUBT | E32: Bill Id | G32: 1020529
A33: 45973 | B33: NOV | C33: DOUBT | E33: Bill Id | F33: 15957.5
A34: 45988 | B34: NOV | C34: DOUBT | E34: Bill Id | G34: 1178837
A35: 45988 | B35: NOV | C35: DOUBT | E35: Bill Id | F35: 17360.5
A36: 46031 | B36: JAN | C36: DOUBT | E36: Bill Id | G36: 769422
A37: 46031 | B37: JAN | C37: DOUBT | E37: Bill Id | G37: 3756345
A38: 46031 | B38: JAN | C38: DOUBT | E38: Bill Id | F38: 12508.5
A39: 46031 | B39: JAN | C39: DOUBT | E39: Bill Id | F39: 48786.5
A40: 45939 | B40: OCT | C40: DOUBT | E40: eBank | F40: 75000
A41: 45904 | B41: SEP | C41: DOUBT | E41: TIN | F41: 1282
A42: 45904 | B42: SEP | C42: DOUBT | E42: TIN | F42: 150575
A43: 45937 | B43: OCT | C43: DOUBT | E43: TIN | F43: 2112
A44: 45937 | B44: OCT | C44: DOUBT | E44: TIN | F44: 55050
A45: 45968 | B45: NOV | C45: DOUBT | E45: TIN | F45: 1266
A46: 45968 | B46: NOV | C46: DOUBT | E46: TIN | F46: 125201
A47: 45996 | B47: DEC | C47: DOUBT | E47: TIN | F47: 133636
A48: 46029 | B48: JAN | C48: DOUBT | E48: TIN | F48: 123663

Sheet BANK FIN
C1: TMB-5048-CA
A2: Date | B2: MONTH | C2: TYPE | D2: Cheque_No | E2: Category | F2: DR | G2: CR
A3: 45999 | B3: DEC | C3: BANK FIN | E3: Gold Loan Disbursed -0227 | G3: 500000
B4: JAN(26)
A6: Date | B6: MONTH | C6: TYPE | D6: Cheque_No | E6: Category | F6: DR | G6: CR
A7: 46034 | B7: JAN(26) | C7: BANK FIN | E7: Gold Loan Disbursed -0320 | G7: 350000
A9: Date | B9: MONTH | C9: TYPE | D9: Cheque_No | E9: Category | F9: DR | G9: CR
A10: 46035 | B10: JAN(26) | C10: BANK FIN | E10: Gold Loan Disbursed -0323 | G10: 335000
A11: Date | B11: MONTH | C11: TYPE | D11: Cheque_No | E11: Category | F11: DR | G11: CR
A12: 45976 | B12: NOV | C12: BANK FIN | E12: Gold Loan Disbursed -2301 | G12: 1375000
A13: 46015 | B13: DEC | C13: BANK FIN | E13: Loan -2301 | F13: 1395294
E14: TOTAL | F14: =SUM(F12:F13) -> 1395294 | G14: =SUM(G12:G13) -> 1375000
A15: Date | B15: MONTH | C15: TYPE | D15: Cheque_No | E15: Category | F15: DR | G15: CR
A16: 45881 | B16: AUG | C16: BANK FIN | E16: Loan -0057 | F16: 42004
A17: 45912 | B17: SEP | C17: BANK FIN | E17: Loan -0057 | F17: 42004
A18: 45942 | B18: OCT | C18: BANK FIN | E18: Loan -0057 | F18: 42004
A19: 45973 | B19: NOV | C19: BANK FIN | E19: Loan -0057 | F19: 24431.96
A20: 45973 | B20: NOV | C20: BANK FIN | E20: Loan -0057 | F20: 17572.04
A21: 46003 | B21: DEC | C21: BANK FIN | E21: Loan -0057 | F21: 42004
A22: 46034 | B22: JAN(26) | C22: BANK FIN | E22: Loan -0057 | F22: 42004
E23: TOTAL | F23: =SUM(F16:F22) -> 252024
A24: Date | B24: MONTH | C24: TYPE | D24: Cheque_No | E24: Category | F24: DR | G24: CR
A25: 45892 | B25: AUG | C25: BANK FIN | E25: Loan -0063 | F25: 12616
A26: 45906 | B26: SEP | C26: BANK FIN | E26: Loan -0063 | F26: 59
A27: 45923 | B27: SEP | C27: BANK FIN | E27: Loan -0063 | F27: 12616
A28: 45953 | B28: OCT | C28: BANK FIN | E28: Loan -0063 | F28: 13242
A29: 45984 | B29: NOV | C29: BANK FIN | E29: Loan -0063 | F29: 13242
A30: 46014 | B30: DEC | C30: BANK FIN | E30: Loan -0063 | F30: 13242
B31: JAN(26)
E32: TOTAL | F32: =SUM(F24:F30) -> 65017
A33: Date | B33: MONTH | C33: TYPE | D33: Cheque_No | E33: Category | F33: DR | G33: CR
B34: AUG
B35: SEP
B36: OCT
A37: 45976 | B37: NOV | C37: BANK FIN | E37: Loan -1923 | F37: 1373868.1
B38: DEC
B39: JAN(26)
C50: TMB-0123-OD
A51: Date | B51: MONTH | C51: TYPE | D51: Cheque_No | E51: Category | F51: DR | G51: CR
A52: 45900 | B52: AUG | C52: BANK FIN | E52: Interest Charges | F52: 336463
A53: 45930 | B53: SEP | C53: BANK FIN | E53: Interest Charges | F53: 316422
A54: 45961 | B54: OCT | C54: BANK FIN | E54: Interest Charges | F54: 327291
A55: 45991 | B55: NOV | C55: BANK FIN | E55: Interest Charges | F55: 316471
A56: 46022 | B56: DEC | C56: BANK FIN | E56: Interest Charges | F56: 327926
E57: TOTAL | F57: =SUM(F52:F56) -> 1624573

Sheet PVT FIN
C1: TMB-5048-CA
A2: Date | B2: MONTH | C2: TYPE | D2: Cheque_No | E2: Category | F2: DR | G2: CR
D3: ACC 1
A4: 45883 | B4: AUG | C4: PVT FIN | D4: 1544086 | E4: ARUL A | F4: 20000
A5: 45916 | B5: SEP | C5: PVT FIN | D5: 1544130 | E5: ARUL A | F5: 20000
A6: 45953 | B6: OCT | C6: PVT FIN | D6: 1544182 | E6: ARUL A | F6: 20000
A7: 45976 | B7: NOV | C7: PVT FIN | D7: 1544215 | E7: ARUL A | F7: 20000
A8: 46006 | B8: DEC | C8: PVT FIN | D8: 1568115 | E8: ARUL A | F8: 20000
A9: 46031 | B9: JAN(26) | C9: PVT FIN | D9: 1568825 | E9: ARUL A | F9: 20000
E10: TOTAL | F10: =SUM(F4:F9) -> 120000
D11: ACC 2
A12: 45999 | B12: DEC | C12: PVT FIN | D12: 1568106 | E12: ARUL A | F12: 300000
D13: ACC 3
A14: 46015 | B14: DEC | C14: PVT FIN | D14: RTGS | E14: ARUL A | G14: 890000
A15: 46034 | B15: JAN(26) | C15: PVT FIN | D15: 1568830 | E15: ARUL A | F15: 350000
A16: 46035 | B16: JAN(26) | C16: PVT FIN | D16: 1568832 | E16: ARUL A | F16: 335000
E17: TOTAL | F17: =SUM(F14:F16) -> 685000 | G17: =SUM(G14:G16) -> 890000
A18: Date | B18: MONTH | C18: TYPE | D18: Cheque_No | E18: Category | F18: DR | G18: CR
A19: 45871 | B19: AUG | C19: PVT FIN | D19: 1544060 | E19: ILAKKIA | F19: 113000
A20: 45902 | B20: SEP | C20: PVT FIN | D20: 1544108 | E20: ILAKKIA | F20: 113000
A21: 45933 | B21: OCT | C21: PVT FIN | D21: 1544156 | E21: ILAKKIA | F21: 113000
A22: 45964 | B22: NOV | C22: PVT FIN | D22: 1544193 | E22: ILAKKIA | F22: 113000
A23: 45994 | B23: DEC | C23: PVT FIN | D23: 1568091 | E23: ILAKKIA | F23: 113000
A24: 46024 | B24: JAN(26) | C24: PVT FIN | D24: 1568810 | E24: ILAKKIA | F24: 113000
E25: TOTAL | F25: =SUM(F19:F24) -> 678000
A26: Date | B26: MONTH | C26: TYPE | D26: Cheque_No | E26: Category | F26: DR | G26: CR
A27: 45874 | B27: AUG | C27: PVT FIN | D27: 1544063 | E27: PREETHI G | F27: 100000
A28: 45904 | B28: SEP | C28: PVT FIN | D28: 1544113 | E28: PREETHI G | F28: 100000
A29: 45940 | B29: OCT | C29: PVT FIN | D29: 1544173 | E29: PREETHI G | F29: 100000
A30: 45971 | B30: NOV | C30: PVT FIN | D30: 1544205 | E30: PREETHI G | F30: 100000
A31: 45997 | B31: DEC | C31: PVT FIN | D31: 1568100 | E31: PREETHI G | F31: 100000
A32: 46031 | B32: JAN(26) | C32: PVT FIN | D32: 1568823 | E32: PREETHI G | F32: 100000
E33: TOTAL | F33: =SUM(F27:F32) -> 600000
C47: TMB-0123-OD
A48: Date | B48: MONTH | C48: TYPE | D48: Cheque_No | E48: Category | F48: DR | G48: CR
A49: 45881 | B49: AUG | C49: PVT FIN | E49: CROWN TRADER | F49: 1250000
B50: SEP
B51: OCT
B52: NOV
B53: DEC
B54: JAN
A56: Date | B56: MONTH | C56: TYPE | D56: Cheque_No | E56: Category | F56: DR | G56: CR
A57: 45881 | B57: AUG | C57: PVT FIN | E57: ROYAL AGENCY | F57: 1250000
B58: SEP
B59: OCT
B60: NOV
B61: DEC
B62: JAN
A64: Date | B64: MONTH | C64: TYPE | D64: Cheque_No | E64: Category | F64: DR | G64: CR
A65: 45890 | B65: AUG | C65: PVT FIN | E65: ADIMOOLAM N | G65: 4400000
A66: 45890 | B66: AUG | C66: PVT FIN | E66: ADIMOOLAM N | G66: 10000000
A67: 45890 | B67: AUG | C67: PVT FIN | E67: GUNA S | G67: 3600000
A68: 46036 | B68: JAN | C68: PVT FIN | E68: ADIMOOLAM N | F68: 8000000
E69: TOTAL | F69: =SUM(F65:F68) -> 8000000 | G69: =SUM(G65:G68) -> 18000000
A70: Date | B70: MONTH | C70: TYPE | D70: Cheque_No | E70: Category | F70: DR | G70: CR
B71: AUG
B72: SEP
B73: OCT
A74: 45967 | B74: NOV | C74: PVT FIN | E74: GLOBAL ENTERPRISE | F74: 2500000
A75: 45996 | B75: DEC | C75: PVT FIN | E75: GLOBAL ENTERPRISE | F75: 2500000
A76: 46027 | B76: JAN | C76: PVT FIN | E76: GLOBAL ENTERPRISE | F76: 2500000
E77: TOTAL | F77: =SUM(F71:F76) -> 7500000
A78: Date | B78: MONTH | C78: TYPE | D78: Cheque_No | E78: Category | F78: DR | G78: CR
A79: 46009 | B79: DEC | C79: PVT FIN | E79: BARATHKUMAR | G79: 495000
A80: 46009 | B80: DEC | C80: PVT FIN | E80: BARATHKUMAR | G80: 495000
B81: JAN
E82: TOTAL | G82: =SUM(G79:G80) -> 990000

Sheet RETURN
C1: TMB-5048-CA
A2: Date | B2: MONTH | C2: TYPE | D2: Cheque_No | E2: Category | F2: DR | G2: CR
A3: 45940 | B3: OCT | C3: RETURN | E3: I/W RTGS RTN -(NOT REP) | G3: 409422
C12: TMB-0123-OD
A13: Date | B13: MONTH | C13: TYPE | D13: Cheque_No | E13: Category | F13: DR | G13: CR
A14: 45881 | B14: AUG | C14: RETURN | E14: I/W CHQ RTN CHG | F14: 2212.5
A15: 45881 | B15: AUG | C15: RETURN | E15: I/W CHQ RTN CHG | F15: 2212.5
A16: 45966 | B16: NOV | C16: RETURN | E16: I/W CHQ RTN CHG | F16: 4425
A17: 46006 | B17: DEC | C17: RETURN | E17: I/W CHQ RTN CHG | F17: 3540
A18: 46022 | B18: DEC | C18: RETURN | E18: I/W CHQ RTN CHG | F18: 885

Sheet PIVOT-TMB-5048-CA
D1: AFFAN METALS TMB-5048-CA
A5: ANALYSED BY POOJA SRI (3.15 TO 4.20 PM)
C6: MONTH | D6: Values
C7: AUG | E7: SEP | G7: OCT | I7: NOV | K7: DEC | M7: JAN(26) | O7: (blank) | Q7: Total Sum of DR | R7: Total Sum of CR
A8: TYPE | B8: Category | C8: Sum of DR | D8: Sum of CR | E8: Sum of DR | F8: Sum of CR | G8: Sum of DR | H8: Sum of CR | I8: Sum of DR | J8: Sum of CR | K8: Sum of DR | L8: Sum of CR | M8: Sum of DR | N8: Sum of CR | O8: Sum of DR | P8: Sum of CR
A9: CASH | B9: CASH WITHDRAWAL | C9: 2.25 | D9: 0 | E9: 6.5 | F9: 0 | G9: 0.5 | H9: 0 | I9: 5.8 | J9: 0 | K9: 4.5 | L9: 0 | Q9: 19.55 | R9: 0
A10: CASH Total | C10: 2.25 | D10: 0 | E10: 6.5 | F10: 0 | G10: 0.5 | H10: 0 | I10: 5.8 | J10: 0 | K10: 4.5 | L10: 0 | Q10: 19.55 | R10: 0
A11: SIS CON | B11: VEERA INDUSTRIES-TMB-0123-OD | C11: 96.7 | D11: 107.1 | E11: 56 | F11: 37.5 | G11: 4.3 | H11: 46.2 | I11: 28.85 | J11: 110.2 | K11: 7.5 | L11: 52 | M11: 35 | N11: 63 | Q11: 228.35 | R11: 416
A12: SIS CON Total | C12: 96.7 | D12: 107.1 | E12: 56 | F12: 37.5 | G12: 4.3 | H12: 46.2 | I12: 28.85 | J12: 110.2 | K12: 7.5 | L12: 52 | M12: 35 | N12: 63 | Q12: 228.35 | R12: 416
A13: ODD FIG | B13: LATHA | C13: 0 | D13: 12 | E13: 0 | F13: 7.8 | Q13: 0 | R13: 19.8
B14: NATARAJAN M | C14: 0 | D14: 25.5 | K14: 0 | L14: 4 | Q14: 0 | R14: 29.5
B15: SRINIVAS K R | C15: 0 | D15: 25.00001 | E15: 0 | F15: 38 | Q15: 0 | R15: 63.00001
B16: UTHIRIYA PRADEE | C16: 0 | D16: 0.5 | E16: 0 | F16: 18.4 | Q16: 0 | R16: 18.9
B17: VELMURUHAN | C17: 0 | D17: 29.00002 | E17: 0 | F17: 3 | Q17: 0 | R17: 32.00002
B18: VENKATESAN | C18: 0 | D18: 15 | Q18: 0 | R18: 15
A19: ODD FIG Total | C19: 0 | D19: 107.00003 | E19: 0 | F19: 67.2 | K19: 0 | L19: 4 | Q19: 0 | R19: 178.20003
A20: DOUBT | B20: BUILDING APPROVAL | M20: 10.105 | N20: 0 | Q20: 10.105 | R20: 0
B21: ITDTAX REFUND | K21: 0 | L21: 34.2159 | M21: 0 | N21: 0.82443 | Q21: 0 | R21: 35.04033
A22: DOUBT Total | K22: 0 | L22: 34.2159 | M22: 10.105 | N22: 0.82443 | Q22: 10.105 | R22: 35.04033
A23: BANK FIN | B23: Gold Loan Disbursed -0227 | K23: 0 | L23: 5 | Q23: 0 | R23: 5
B24: Gold Loan Disbursed -0320 | M24: 0 | N24: 3.5 | Q24: 0 | R24: 3.5
B25: Gold Loan Disbursed -0323 | M25: 0 | N25: 3.35 | Q25: 0 | R25: 3.35
B26: Gold Loan Disbursed -2301 | I26: 0 | J26: 13.75 | Q26: 0 | R26: 13.75
B27: Loan -0057 | C27: 0.42004 | D27: 0 | E27: 0.42004 | F27: 0 | G27: 0.42004 | H27: 0 | I27: 0.42004 | J27: 0 | K27: 0.42004 | L27: 0 | M27: 0.42004 | N27: 0 | Q27: 2.52024 | R27: 0
B28: Loan -0063 | C28: 0.12616 | D28: 0 | E28: 0.12675 | F28: 0 | G28: 0.13242 | H28: 0 | I28: 0.13242 | J28: 0 | K28: 0.13242 | L28: 0 | Q28: 0.65017 | R28: 0
B29: Loan -1923 | I29: 13.738681 | J29: 0 | Q29: 13.738681 | R29: 0
B30: Loan -2301 | K30: 13.95294 | L30: 0 | Q30: 13.95294 | R30: 0
A31: BANK FIN Total | C31: 0.5462 | D31: 0 | E31: 0.54679 | F31: 0 | G31: 0.55246 | H31: 0 | I31: 14.291141 | J31: 13.75 | K31: 14.5054 | L31: 5 | M31: 0.42004 | N31: 6.85 | Q31: 30.862031 | R31: 25.6
A32: PVT FIN | B32: ARUL A | C32: 0.2 | D32: 0 | E32: 0.2 | F32: 0 | G32: 0.2 | H32: 0 | I32: 0.2 | J32: 0 | K32: 3.2 | L32: 8.9 | M32: 7.05 | N32: 0 | Q32: 11.05 | R32: 8.9
B33: ILAKKIA | C33: 1.13 | D33: 0 | E33: 1.13 | F33: 0 | G33: 1.13 | H33: 0 | I33: 1.13 | J33: 0 | K33: 1.13 | L33: 0 | M33: 1.13 | N33: 0 | Q33: 6.78 | R33: 0
B34: PREETHI G | C34: 1 | D34: 0 | E34: 1 | F34: 0 | G34: 1 | H34: 0 | I34: 1 | J34: 0 | K34: 1 | L34: 0 | M34: 1 | N34: 0 | Q34: 6 | R34: 0
A35: PVT FIN Total | C35: 2.33 | D35: 0 | E35: 2.33 | F35: 0 | G35: 2.33 | H35: 0 | I35: 2.33 | J35: 0 | K35: 5.33 | L35: 8.9 | M35: 9.18 | N35: 0 | Q35: 23.83 | R35: 8.9
A36: RETURN | B36: I/W RTGS RTN -(NOT REP) | G36: 0 | H36: 4.09422 | Q36: 0 | R36: 4.09422
A37: RETURN Total | G37: 0 | H37: 4.09422 | Q37: 0 | R37: 4.09422
A38: Insurance | B38: Insurance | G38: 0.2298339 | H38: 0 | Q38: 0.2298339 | R38: 0
A39: Insurance Total | G39: 0.2298339 | H39: 0 | Q39: 0.2298339 | R39: 0
A40: EXPENSES | B40: Bank Charges | E40: 0.00885 | F40: 0 | I40: 0.002 | J40: 0 | K40: 0.002 | L40: 0 | M40: 0.004 | N40: 0 | Q40: 0.01685 | R40: 0
B41: Tax | C41: 5.97897 | D41: 0 | E41: 4.64163 | F41: 0 | G41: 7.73483 | H41: 0 | I41: 7.70143 | J41: 0 | K41: 5.58567 | L41: 0 | M41: 4.22484 | N41: 0 | Q41: 35.86737 | R41: 0
A42: EXPENSES Total | C42: 5.97897 | D42: 0 | E42: 4.65048 | F42: 0 | G42: 7.73483 | H42: 0 | I42: 7.70343 | J42: 0 | K42: 5.58767 | L42: 0 | M42: 4.22884 | N42: 0 | Q42: 35.88422 | R42: 0
A43: PURCHASE | B43: AROKIYA TRADERS | C43: 2.86 | D43: 0 | G43: 3.475 | H43: 0 | Q43: 6.335 | R43: 0
B44: BADRINATH | C44: 0.5 | D44: 0 | Q44: 0.5 | R44: 0
B45: COMPANY NAME | C45: 0.5506954 | D45: 0 | E45: 0.6320421 | F45: 0 | G45: 0.6243497 | H45: 0 | I45: 1.0276862 | J45: 0 | K45: 0.433 | L45: 0 | M45: 0.6496808 | N45: 0 | Q45: 3.9174542 | R45: 0
B46: DHANALAKSHMI RAJKA | C46: 1 | D46: 0 | E46: 0.7 | F46: 0 | G46: 1 | H46: 0 | I46: 1 | J46: 0 | K46: 0.5 | L46: 0 | Q46: 4.2 | R46: 0
B47: JOTHI LAKSHMI.E | E47: 1.5 | F47: 0 | Q47: 1.5 | R47: 0
B48: K S S ENTERPRISES | C48: 9.26 | D48: 0 | E48: 1.66 | F48: 0 | G48: 1.31 | H48: 0 | I48: 3.05 | J48: 0 | K48: 3.19 | L48: 0 | M48: 2.02 | N48: 0 | Q48: 20.49 | R48: 0
B49: KANNAN | C49: 0.83308 | D49: 0 | E49: 0.90904 | F49: 0 | G49: 0.70968 | H49: 0 | I49: 0.71926 | J49: 0 | K49: 0.69294 | L49: 0 | M49: 0.69306 | N49: 0 | Q49: 4.55706 | R49: 0
B50: MARIYA CHRISTY RATHIKA | M50: 1 | N50: 0 | Q50: 1 | R50: 0
B51: NAVANEETHAN RAJKAN | I51: 0.5 | J51: 0 | K51: 0.4 | L51: 0 | Q51: 0.9 | R51: 0
B52: PANDURANGAN | C52: 1.73252 | D52: 0 | E52: 0.12855 | F52: 0 | G52: 1.44035 | H52: 0 | I52: 0.61399 | J52: 0 | K52: 0.83741 | L52: 0 | M52: 1.824 | N52: 0 | Q52: 6.57682 | R52: 0
B53: PANKAJ ACHARYA | I53: 0.625 | J53: 0 | K53: 0.55 | L53: 0 | Q53: 1.175 | R53: 0
B54: PRIYADHARSHINI SUR | G54: 0.5 | H54: 0 | Q54: 0.5 | R54: 0
B55: RAJKANTH JAYARAM | C55: 1.25 | D55: 0 | E55: 0.4 | F55: 0 | G55: 1 | H55: 0 | K55: 0.5 | L55: 0 | Q55: 3.15 | R55: 0
B56: RAMAJAYAM | C56: 5.37126 | D56: 0 | E56: 4.61134 | F56: 0 | G56: 3.32896 | H56: 0 | I56: 3.8758 | J56: 0 | K56: 4.197 | L56: 0 | M56: 3.9133 | N56: 0 | Q56: 25.29766 | R56: 0
B57: SAMVARDHANA MOTHER | C57: 232.66752 | D57: 0 | E57: 203.50337 | F57: 0 | G57: 150.18256 | H57: 0 | I57: 98.99098 | J57: 0 | K57: 144.59044 | L57: 0 | M57: 93.87398 | N57: 0 | Q57: 923.80885 | R57: 0
B58: SARALA B | I58: 1 | J58: 0 | Q58: 1 | R58: 0
B59: SARAVANAN M | C59: 0.94232 | D59: 0 | E59: 1.2757 | F59: 0 | G59: 1.31558 | H59: 0 | I59: 1.3657 | J59: 0 | K59: 1.4244 | L59: 0 | M59: 1.26528 | N59: 0 | Q59: 7.58898 | R59: 0
B60: SIVARAJANI CHENGUT | I60: 0.5 | J60: 0 | Q60: 0.5 | R60: 0
B61: SMS AND ASSEMBLIES | C61: 96 | D61: 0 | E61: 176.5 | F61: 0 | G61: 143.5 | H61: 0 | I61: 250.90998 | J61: 0 | K61: 160.17369 | L61: 0 | M61: 36 | N61: 0 | Q61: 863.08367 | R61: 0
B62: SRI PACHAIYAMMAN B | E62: 1 | F62: 0 | Q62: 1 | R62: 0
B63: SURESH BABU D | C63: 1.5 | D63: 0 | Q63: 1.5 | R63: 0
B64: TAMILSELVAN G | C64: 0.1 | D64: 0 | E64: 0.1 | F64: 0 | G64: 0.1 | H64: 0 | I64: 0.1 | J64: 0 | K64: 0.1 | L64: 0 | M64: 0.1 | N64: 0 | Q64: 0.6 | R64: 0
B65: VICTORY SCALES | I65: 1.8 | J65: 0 | Q65: 1.8 | R65: 0
B66: VIHAAN | G66: 0.4 | H66: 0 | I66: 0.4 | J66: 0 | K66: 1 | L66: 0 | Q66: 1.8 | R66: 0
B67: VINOD KUMAR | C67: 1.66 | D67: 0 | E67: 0.66 | F67: 0 | G67: 0.66 | H67: 0 | I67: 0.66 | J67: 0 | K67: 0.66 | L67: 0 | M67: 0.66 | N67: 0 | Q67: 4.96 | R67: 0
B68: XAVIERDAS.A | E68: 0.2 | F68: 0 | K68: 0.07 | L68: 0 | M68: 0.6 | N68: 0 | Q68: 0.87 | R68: 0
A69: PURCHASE Total | C69: 356.2274 | D69: 0 | E69: 393.78004 | F69: 0 | G69: 309.54648 | H69: 0 | I69: 367.1384 | J69: 0 | K69: 319.31888 | L69: 0 | M69: 142.5993 | N69: 0 | Q69: 1888.6105 | R69: 0
A70: SALES | B70: ANANDH S | E70: 0 | F70: 14.82 | Q70: 0 | R70: 14.82
B71: CASH DEPOSIT | I71: 0 | J71: 17 | K71: 0 | L71: 7 | Q71: 0 | R71: 24
B72: COMPANY NAME | E72: 0 | F72: 0.35001 | Q72: 0 | R72: 0.35001
B73: DHANUPRAKASH | C73: 0 | D73: 16 | Q73: 0 | R73: 16
B74: DHARMARAJ | E74: 0 | F74: 8.52 | Q74: 0 | R74: 8.52
B75: GOPINATH P T | C75: 0 | D75: 10 | E75: 0 | F75: 7 | Q75: 0 | R75: 17
B76: INFANT RAJ R | E76: 0 | F76: 13.5 | Q76: 0 | R76: 13.5
B77: K S S ENTERPRISES | G77: 0 | H77: 35 | I77: 0 | J77: 22 | K77: 0 | L77: 5 | Q77: 0 | R77: 62
B78: M S A ENTERP | E78: 0 | F78: 3 | G78: 0 | H78: 3 | Q78: 0 | R78: 6
B79: METAL AND SC | C79: 0 | D79: 59.23594 | E79: 0 | F79: 67.24169 | G79: 0 | H79: 0.5138 | Q79: 0 | R79: 126.99143
B80: MTC BUSINESS | C80: 0 | D80: 95.43429 | E80: 0 | F80: 125.74519 | G80: 0 | H80: 187.10532 | I80: 0 | J80: 195.28158 | K80: 0 | L80: 150.55706 | M80: 0 | N80: 55.21775 | Q80: 0 | R80: 809.34119
B81: MURUGANANTHA | E81: 0 | F81: 7.18 | Q81: 0 | R81: 7.18
B82: PUSHPANATAHAN | C82: 0 | D82: 12.5 | Q82: 0 | R82: 12.5
B83: S S S TRADER | E83: 0 | F83: 5.557436 | Q83: 0 | R83: 5.557436
B84: SRI AMBAL TRADE | C84: 0 | D84: 19.97752 | E84: 0 | F84: 55.51178 | G84: 0 | H84: 51 | I84: 0 | J84: 45.80773 | K84: 0 | L84: 65.30937 | M84: 0 | N84: 14 | Q84: 0 | R84: 251.6064
B85: SRI SAI ENTERPRISE | C85: 0 | D85: 25 | E85: 0 | F85: 25 | I85: 0 | J85: 25 | K85: 0 | L85: 50 | M85: 0 | N85: 10.176342 | Q85: 0 | R85: 135.17634
B86: SRI SUN ENTE | C86: 0 | D86: 25 | M86: 0 | N86: 30 | Q86: 0 | R86: 55
B87: VIKNESH KARM | E87: 0 | F87: 17.28 | Q87: 0 | R87: 17.28
A88: SALES Total | C88: 0 | D88: 263.14775 | E88: 0 | F88: 350.70611 | G88: 0 | H88: 276.61912 | I88: 0 | J88: 305.08931 | K88: 0 | L88: 277.86643 | M88: 0 | N88: 109.39409 | Q88: 0 | R88: 1582.8228
A89: (blank) | B89: (blank)
A90: (blank) Total
A91: Grand Total | C91: 464.03257 | D91: 477.24778 | E91: 463.80731 | F91: 455.40611 | G91: 325.1936 | H91: 326.91334 | I91: 426.11297 | J91: 429.03931 | K91: 356.74195 | L91: 381.98233 | M91: 201.53318 | N91: 180.06852 | Q91: 2237.4216 | R91: 2250.6574

Sheet XNS-TMB-5048-CA
A1: Sl. No. | B1: Date | C1: MONTH | D1: TYPE | E1: Cheque_No | F1: Category | G1: Description | H1: DR | I1: CR | J1: Balance
A2: 1 | B2: 45870 | C2: AUG | D2: SALES | F2: METAL AND SC | G2: RTGS/METAL AND SC/HDFCR52025080196730628 | H2: 0 | I2: 2.5 | J2: 305906.55
A3: 2 | B3: 45870 | C3: AUG | D3: SIS CON | F3: VEERA INDUSTRIES-TMB-0123-OD | G3: TR/CHEPA/VEERAVINDUSTRIES (Ref# 1544058) | H3: 2.95 | I3: 0 | J3: 10906.55
A4: 3 | B4: 45870 | C4: AUG | D4: SALES | F4: MTC BUSINESS | G4: RTGS/MTC BUSINESS/HDFCR52025080196836729 | H4: 0 | I4: 9.04558 | J4: 915464.55
A5: 4 | B5: 45870 | C5: AUG | D5: SIS CON | F5: VEERA INDUSTRIES-TMB-0123-OD | G5: TR/CHEPA/VEERA INDUSTRIES | H5: 0 | I5: 18 | J5: 2715464.5
A6: 5 | B6: 45870 | C6: AUG | D6: PURCHASE | F6: SAMVARDHANA MOTHER | G6: RTGS/SAMVARDHANA /TMBLR52025080100480511 (Ref# 1544059) | H6: 26 | I6: 0 | J6: 115464.55
A7: 6 | B7: 45871 | C7: AUG | D7: SALES | F7: METAL AND SC | G7: NEFT/METAL AND SCRAP TR/HDFCH00398392264 | H7: 0 | I7: 0.20464 | J7: 135928.55 | M7: 100000
A8: 7 | B8: 45871 | C8: AUG | D8: SIS CON | F8: VEERA INDUSTRIES-TMB-0123-OD | G8: TR/CHEPA/VEERA INDUSTRIES | H8: 0 | I8: 0.1 | J8: 145928.55
A9: 8 | B9: 45871 | C9: AUG | D9: PVT FIN | E9: 1544060 | F9: ILAKKIA | G9: TR/CHEPA/ILAKKIA (Ref# 1544060) | H9: 1.13 | I9: 0 | J9: 32928.55
A10: 9 | B10: 45873 | C10: AUG | D10: SIS CON | F10: VEERA INDUSTRIES-TMB-0123-OD | G10: TR/CHEPA/VEERA INDUSTRIES | H10: 0 | I10: 42 | J10: 4232928.5
A11: 10 | B11: 45873 | C11: AUG | D11: PURCHASE | F11: SAMVARDHANA MOTHER | G11: RTGS/SAMVARDHANA /TMBLR52025080400763940 (Ref# 1544061) | H11: 39.44783 | I11: 0 | J11: 288145.55
A12: 11 | B12: 45873 | C12: AUG | D12: PURCHASE | F12: SURESH BABU D | G12: NEFT/SURESH BABU D/TMBLH25216790013 (Ref# 1544062) | H12: 1.5 | I12: 0 | J12: 138145.55
A13: 12 | B13: 45873 | C13: AUG | D13: SIS CON | F13: VEERA INDUSTRIES-TMB-0123-OD | G13: eBank/Tr From VEERA INDUSTRIES / TRANSFER TO AFFAN | H13: 0 | I13: 15 | J13: 1638145.6
A14: 13 | B14: 45873 | C14: AUG | D14: PURCHASE | F14: K S S ENTERPRISES | G14: eBank/Tr To K S S ENTERPRISES / TRANSFER TO KSS | H14: 7.74 | I14: 0 | J14: 864145.55
A15: 14 | B15: 45874 | C15: AUG | D15: ODD FIG | F15: SRINIVAS K R | G15: IMPS/K R SRINIVASAN/521709099587/ICIC/testac | H15: 0 | I15: 1e-05 | J15: 864146.55
A16: 15 | B16: 45874 | C16: AUG | D16: SALES | F16: METAL AND SC | G16: RTGS/METAL AND SC/HDFCR52025080597844065 | H16: 0 | I16: 6.5 | J16: 1514146.6
A17: 16 | B17: 45874 | C17: AUG | D17: PURCHASE | F17: RAMAJAYAM | G17: RTGS/RAMAJAYAM/TMBLR52025080500909634 | H17: 2.37126 | I17: 0 | J17: 1277020.6
A18: 17 | B18: 45874 | C18: AUG | D18: PURCHASE | F18: SARAVANAN M | G18: NEFT/SARAVANAN M/TMBLH25217909770 | H18: 0.94232 | I18: 0 | J18: 1182788.6
A19: 18 | B19: 45874 | C19: AUG | D19: PURCHASE | F19: KANNAN | G19: NEFT/KANNAN/TMBLH25217912535 | H19: 0.83308 | I19: 0 | J19: 1099480.6
A20: 19 | B20: 45874 | C20: AUG | D20: PURCHASE | F20: PANDURANGAN | G20: NEFT/PANDURANGAN/TMBLH25217912752 | H20: 1.23252 | I20: 0 | J20: 976228.55
A21: 20 | B21: 45874 | C21: AUG | D21: PURCHASE | F21: VINOD KUMAR | G21: NEFT/vinod kumar/TMBLH25217912843 | H21: 0.66 | I21: 0 | J21: 910228.55
... A23: 22 | B23: 45874 | C23: AUG | D23: PURCHASE | F23: COMPANY NAME | G23: TR/CHEPA/DEVARAJU RAJAMAIKKAM (Ref# 1544064) | H23: 0.2 | I23: 0 | J23: 3390228.5
A24: 23 | B24: 45874 | C24: AUG | D24: PVT FIN | E24: 1544063 | F24: PREETHI G | G24: NEFT/G PREETHI/TMBLH25217926757 (Ref# 1544063) | H24: 1 | I24: 0 | J24: 3290228.5
A25: 24 | B25: 45874 | C25: AUG | D25: PURCHASE | F25: SMS AND ASSEMBLIES | G25: RTGS/SMS And Assemblies/TMBLR52025080500926949 | H25: 14 | I25: 0 | J25: 1890228.6
A26: 25 | B26: 45874 | C26: AUG | D26: PURCHASE | F26: COMPANY NAME | G26: eBank/613285161/MR.XAVIER HOME EB | H26: 0.1913954 | I26: 0 | J26: 1871089
A27: 26 | B27: 45874 | C27: AUG | D27: SIS CON | F27: VEERA INDUSTRIES-TMB-0123-OD | G27: TR/CHEPA/VEERA INDUSTRIES (Ref# 1544071) | H27: 18 | I27: 0 | J27: 71089.01
A28: 27 | B28: 45875 | C28: AUG | D28: SALES | F28: METAL AND SC | G28: RTGS/METAL AND SC/HDFCR52025080698347462 | H28: 0 | I28: 5 | J28: 571089.01
A29: 28 | B29: 45875 | C29: AUG | D29: SALES | F29: DHANUPRAKASH | G29: IMPS/DHANUPRAKASH/521813310106/HDFC/Payment | H29: 0 | I29: 0.01 | J29: 572089.01
A30: 29 | B30: 45875 | C30: AUG | D30: SALES | F30: MTC BUSINESS | G30: RTGS/MTC BUSINESS/HDFCR52025080698318817 | H30: 0 | I30: 13.80475 | J30: 1952564
A31: 30 | B31: 45875 | C31: AUG | D31: ODD FIG | F31: VENKATESAN | G31: RTGS/VENKATESAN/CBINR52025080610009959 | H31: 0 | I31: 10 | J31: 2952564
A32: 31 | B32: 45875 | C32: AUG | D32: ODD FIG | F32: VELMURUHAN | G32: RTGS/VELMURUHAN/SBINR52025080694604171 | H32: 0 | I32: 10 | J32: 3952564
A33: 32 | B33: 45875 | C33: AUG | D33: PURCHASE | F33: SAMVARDHANA MOTHER | G33: RTGS/SAMVARDHANA /TMBLR52025080600104246 (Ref# 1544072) | H33: 15 | I33: 0 | J33: 2452564
A34: 33 | B34: 45875 | C34: AUG | D34: SALES | F34: DHANUPRAKASH | G34: NEFT/DHANUPRAKASH/HDFCH00407581852 | H34: 0 | I34: 4.99 | J34: 2951564
A35: 34 | B35: 45875 | C35: AUG | D35: SALES | F35: PUSHPANATAHAN | G35: NEFT/PUSHPANATAHAN/SBIN425218954034 | H35: 0 | I35: 7.5 | J35: 3701564
A36: 35 | B36: 45875 | C36: AUG | D36: SIS CON | F36: VEERA INDUSTRIES-TMB-0123-OD | G36: eBank/Tr To VEERA INDUSTRIES / TRANSFER TO VEERA | H36: 25 | I36: 0 | J36: 1201564
... A77: 76 | B77: 45883 | C77: AUG | D77: PURCHASE | F77: RAJKANTH JAYARAM | G77: NEFT/RAJKANTH JAYARAM/TMBLH25226052859 (Ref# 1544083) | H77: 1.25 | I77: 0 | J77: 1047288
A78: 77 | B78: 45883 | C78: AUG | D78: PVT FIN | E78: 1544086 | F78: ARUL A | G78: NEFT/A ARUL/TMBLH25226056834 (Ref# 1544086) | H78: 0.2 | I78: 0 | J78: 1027288
A79: 78 | B79: 45883 | C79: AUG | D79: SIS CON | F79: VEERA INDUSTRIES-TMB-0123-OD | G79: TR/CHEPA/VEERA INDUSTRIES (Ref# 1544092) | H79: 3 | I79: 0 | J79: 727288.01
A80: 79 | B80: 45887 | C80: AUG | D80: SALES | F80: METAL AND SC | G80: RTGS/METAL AND SC/HDFCR52025081851656721 | H80: 0 | I80: 4 | J80: 1127288
A81: 80 | B81: 45887 | C81: AUG | D81: SIS CON | F81: VEERA INDUSTRIES-TMB-0123-OD | G81: TR/CHEPA/VEERA INDUSTRIES | H81: 0 | I81: 6 | J81: 1727288
A82: 81 | B82: 45887 | C82: AUG | D82: PURCHASE | F82: COMPANY NAME | G82: NEFT/G S TECHNOLOGIES/TMBLH25230408903 (Ref# 1544094) | H82: 0.1593 | I82: 0 | J82: 1711358
A83: 82 | B83: 45887 | C83: AUG | D83: PURCHASE | F83: SAMVARDHANA MOTHER | G83: RTGS/SAMVARDHANA /TMBLR52025081800410080 (Ref# 1544093) | H83: 12 | I83: 0 | J83: 511358.01
A84: 83 | B84: 45888 | C84: AUG | D84: SALES | F84: METAL AND SC | G84: NEFT/METAL AND SCRAP TR/HDFCH00431655151 | H84: 0 | I84: 0.3605 | J84: 547408.01
A85: 84 | B85: 45888 | C85: AUG | D85: SALES | F85: MTC BUSINESS | G85: RTGS/MTC BUSINESS/HDFCR52025081952129608 | H85: 0 | I85: 4.42223 | J85: 989631.01
A86: 85 | B86: 45888 | C86: AUG | D86: CASH | F86: CASH WITHDRAWAL | G86: CS/CHEPA/SELF (Ref# 1544119) | H86: 0.25 | I86: 0 | J86: 964631.01
A87: 86 | B87: 45888 | C87: AUG | D87: SIS CON | F87: VEERA INDUSTRIES-TMB-0123-OD | G87: TR/CHEPA/VEERA INDUSTRIES | H87: 0 | I87: 2 | J87: 1164631
A88: 87 | B88: 45888 | C88: AUG | D88: PURCHASE | F88: SAMVARDHANA MOTHER | G88: RTGS/SAMVARDHANA /TMBLR52025081900523840 (Ref# 1544095) | H88: 11 | I88: 0 | J88: 64631.01
A89: 88 | B89: 45889 | C89: AUG | D89: SIS CON | F89: VEERA INDUSTRIES-TMB-0123-OD | G89: TR/CHEPA/VEERA INDUSTRIES | H89: 0 | I89: 13 | J89: 1364631
A90: 89 | B90: 45889 | C90: AUG | D90: PURCHASE | F90: K S S ENTERPRISES | G90: TR/CHEPA/K S S ENTERPRISES (Ref# 1544097) | H90: 0.29 | I90: 0 | J90: 1335631
... A145: 144 | B145: 45902 | C145: SEP | D145: SALES | F145: MTC BUSINESS | G145: RTGS/MTC BUSINESS/HDFCR52025090256881804 | H145: 0 | I145: 5.85215 | J145: 2033818
A146: 145 | B146: 45902 | C146: SEP | D146: PVT FIN | E146: 1544108 | F146: ILAKKIA | G146: TR/CHEPA/ILAKKIA (Ref# 1544108) | H146: 1.13 | I146: 0 | J146: 1920818
A147: 146 | B147: 45902 | C147: SEP | D147: SALES | F147: SRI AMBAL TRADE | G147: IMPS/SRI AMBAL TRADE/524516324238/ICIC/AFFANMETAL | H147: 0 | I147: 3.18055 | J147: 2238873
A148: 147 | B148: 45903 | C148: SEP | D148: SALES | F148: METAL AND SC | G148: RTGS/METAL AND SC/HDFCR52025090357231751 | H148: 0 | I148: 2 | J148: 2438873
A149: 148 | B149: 45903 | C149: SEP | D149: PURCHASE | F149: SMS AND ASSEMBLIES | G149: RTGS/SMS And Assemblies/TMBLR52025090300164575 | H149: 10 | I149: 0 | J149: 1438873
A150: 149 | B150: 45903 | C150: SEP | D150: SALES | F150: MTC BUSINESS | G150: RTGS/MTC BUSINESS/HDFCR52025090357263677 | H150: 0 | I150: 2.2754 | J150: 1666413
A151: 150 | B151: 45903 | C151: SEP | D151: SALES | F151: SRI AMBAL TRADE | G151: NEFT/SRI AMBAL TRADERS/ICIN424655771949 | H151: 0 | I151: 3.11096 | J151: 1977509
A152: 151 | B152: 45904 | C152: SEP | D152: SALES | F152: METAL AND SC | G152: RTGS/METAL AND SC/HDFCR52025090457544184 | H152: 0 | I152: 2.5 | J152: 2227509
A153: 152 | B153: 45904 | C153: SEP | D153: SALES | F153: MTC BUSINESS | G153: RTGS/MTC BUSINESS/HDFCR52025090457558769 | H153: 0 | I153: 4.92094 | J153: 2719603
A154: 153 | B154: 45904 | C154: SEP | D154: SALES | F154: SRI AMBAL TRADE | G154: NEFT/SRI AMBAL TRADERS/ICIN424756276492 | H154: 0 | I154: 2.61405 | J154: 2981008
A155: 154 | B155: 45904 | C155: SEP | D155: PURCHASE | F155: SAMVARDHANA MOTHER | G155: RTGS/SAMVARDHANA /TMBLR52025090400293228 (Ref# 1544109) | H155: 10 | I155: 0 | J155: 1981008
A156: 155 | B156: 45904 | C156: SEP | D156: PURCHASE | F156: K S S ENTERPRISES | G156: TR/CHEPA/KSS ENTERPRISES (Ref# 1544110) | H156: 0.1 | I156: 0 | J156: 1971008
A157: 156 | B157: 45904 | C157: SEP | D157: CASH | F157: CASH WITHDRAWAL | G157: CS/CHEPA/SELF (Ref# 1544118) | H157: 1 | I157: 0 | J157: 1871008
A158: 157 | B158: 45904 | C158: SEP | D158: EXPENSES | F158: TAX | G158: TIN/25090400164908/TAX (Ref# 1544111) | H158: 2.81007 | I158: 0 | J158: 1590001
A159: 158 | B159: 45904 | C159: SEP | D159: EXPENSES | F159: TAX | G159: TIN/25090400167418/TAX (Ref# 1544112) | H159: 0.05102 | I159: 0 | J159: 1584899
A160: 159 | B160: 45904 | C160: SEP | D160: PVT FIN | E160: 1544113 | F160: PREETHI G | G160: NEFT/PREETHI G/TMBLH25247333827 (Ref# 1544113) | H160: 1 | I160: 0 | J160: 1484899
A161: 160 | B161: 45905 | C161: SEP | D161: SALES | F161: MTC BUSINESS | G161: RTGS/MTC BUSINESS/HDFCR52025090557994625 | H161: 0 | I161: 2.34559 | J161: 1719458
A162: 161 | B162: 45905 | C162: SEP | D162: PURCHASE | F162: SMS AND ASSEMBLIES | G162: RTGS/SMS And Assemblies/TMBLR52025090500468042 | H162: 15 | I162: 0 | J162: 219458.01
A163: 162 | B163: 45906 | C163: SEP | D163: ODD FIG | F163: SRINIVAS K R | G163: RTGS/K R SRINIVAS/ICICR42025090600501818 | H163: 0 | I163: 14 | J163: 1619458
A164: 163 | B164: 45906 | C164: SEP | D164: SALES | F164: METAL AND SC | G164: RTGS/METAL AND SC/HDFCR52025090658212024 | H164: 0 | I164: 2.5 | J164: 1869458
A165: 164 | B165: 45906 | C165: SEP | D165: SALES | F165: MTC BUSINESS | G165: RTGS/MTC BUSINESS/HDFCR52025090658203644 | H165: 0 | I165: 3.37219 | J165: 2206677
A166: 165 | B166: 45906 | C166: SEP | D166: BANK FIN | F166: Loan -0063 | G166: Loan Coll. To -210700850100063 | H166: 0.00059 | I166: 0 | J166: 2206618
A167: 166 | B167: 45908 | C167: SEP | D167: PURCHASE | F167: SMS AND ASSEMBLIES | G167: RTGS/SMS And Assemblies/TMBLR52025090800735089 | H167: 20 | I167: 0 | J167: 206618.01
A168: 167 | B168: 45908 | C168: SEP | D168: ODD FIG | F168: SRINIVAS K R | G168: RTGS/K R SRINIVAS/ICICR42025090800515136 | H168: 0 | I168: 10 | J168: 1206618
A169: 168 | B169: 45908 | C169: SEP | D169: SALES | F169: METAL AND SC | G169: NEFT/METAL AND SCRAP TR/HDFCH00470740356 | H169: 0 | I169: 0.36263 | J169: 1242881
A170: 169 | B170: 45908 | C170: SEP | D170: PURCHASE | F170: RAJKANTH JAYARAM | G170: NEFT/RAJKANTH JAYARAM/TMBLH25251769453 (Ref# 1544114) | H170: 0.4 | I170: 0 | J170: 1202881
A171: 170 | B171: 45908 | C171: SEP | D171: PURCHASE | F171: DHANALAKSHMI RAJKA | G171: NEFT/DHANALAKSHMI RAJKA/TMBLH25251769484 (Ref# 1544115) | H171: 0.35 | I171: 0 | J171: 1167881
A172: 171 | B172: 45908 | C172: SEP | D172: SALES | F172: SRI AMBAL TRADE | G172: RTGS/SRI AMBAL TR/ICICR42025090800544529 | H172: 0 | I172: 6.0692 | J172: 1774801
... A228: 227 | B228: 45916 | C228: SEP | D228: PURCHASE | F228: TAMILSELVAN G | G228: NEFT/TAMILSELVAN G/TMBLH25259725241 (Ref# 1544131) | H228: 0.1 | I228: 0 | J228: 1083709.9
A229: 228 | B229: 45916 | C229: SEP | D229: PVT FIN | E229: 1544130 | F229: ARUL A | G229: NEFT/A ARUL/TMBLH25259726393 (Ref# 1544130) | H229: 0.2 | I229: 0 | J229: 1063709.9
A230: 229 | B230: 45916 | C230: SEP | D230: PURCHASE | F230: SAMVARDHANA MOTHER | G230: RTGS/SAMVARDHANA /TMBLR52025091600727124 (Ref# 1544133) | H230: 5 | I230: 0 | J230: 563709.94
A231: 230 | B231: 45916 | C231: SEP | D231: PURCHASE | F231: COMPANY NAME | G231: NEFT/SUNDARA SUBBAIAH/TMBLH25259727422 (Ref# 1544135) | H231: 0.353 | I231: 0 | J231: 528409.94
A232: 231 | B232: 45916 | C232: SEP | D232: SIS CON | F232: VEERA INDUSTRIES-TMB-0123-OD | G232: TR/CHEPA/VEERA INDUSTRIES (Ref# 1544134) | H232: 1 | I232: 0 | J232: 428409.94
A233: 232 | B233: 45916 | C233: SEP | D233: SALES | F233: SRI AMBAL TRADE | G233: RTGS/SRI AMBAL TR/ICICR42025091600571827 | H233: 0 | I233: 4.74668 | J233: 903077.94
A234: 233 | B234: 45917 | C234: SEP | D234: ODD FIG | F234: UTHIRIYA PRADEE | G234: IMPS/UTHIRIYA PRADEE/526011967129/IOBA/Loan Repaym | H234: 0 | I234: 2 | J234: 1103077.9
A235: 234 | B235: 45917 | C235: SEP | D235: SALES | F235: VIKNESH KARM | G235: NEFT/VIKNESH/SBIN125260556972 | H235: 0 | I235: 7.4 | J235: 1843077.9
A236: 235 | B236: 45917 | C236: SEP | D236: SIS CON | F236: VEERA INDUSTRIES-TMB-0123-OD | G236: TR/CHEPA/VEERA INDUSTRIES | H236: 0 | I236: 6.5 | J236: 2493077.9
A237: 236 | B237: 45917 | C237: SEP | D237: SALES | F237: MURUGANANTHA | G237: RTGS/MURUGANANTHA/IDIBR52025091747547366 | H237: 0 | I237: 7.18 | J237: 3211077.9
A238: 237 | B238: 45917 | C238: SEP | D238: SALES | F238: METAL AND SC | G238: RTGS/METAL AND SC/HDFCR52025091761719035 | H238: 0 | I238: 2.5 | J238: 3461077.9
A239: 238 | B239: 45917 | C239: SEP | D239: SALES | F239: ANANDH S | G239: RTGS/S. Anandh/IDIBR52025091747547481 | H239: 0 | I239: 5.7 | J239: 4031077.9
A240: 239 | B240: 45917 | C240: SEP | D240: SALES | F240: INFANT RAJ R | G240: RTGS/Infant Raj R/IDIBR52025091747547672 | H240: 0 | I240: 5.4 | J240: 4571077.9
A241: 240 | B241: 45917 | C241: SEP | D241: SALES | F241: MTC BUSINESS | G241: RTGS/MTC BUSINESS/HDFCR52025091761901072 | H241: 0 | I241: 8.4412 | J241: 5415197.9
... A303: 302 | B303: 45933 | C303: OCT | D303: SALES | F303: MTC BUSINESS | G303: RTGS/MTC BUSINESS/HDFCR52025100367708180 | H303: 0 | I303: 6.69568 | J303: 1206875.4
A304: 303 | B304: 45933 | C304: OCT | D304: PVT FIN | E304: 1544156 | F304: ILAKKIA | G304: TR/CHEPA/ILAKKIA (Ref# 1544156) | H304: 1.13 | I304: 0 | J304: 1093875.4
A305: 304 | B305: 45933 | C305: OCT | D305: SIS CON | F305: VEERA INDUSTRIES-TMB-0123-OD | G305: TR/CHEPA/VEERA INDUSTRIES | H305: 0 | I305: 6 | J305: 1693875.4
A306: 305 | B306: 45933 | C306: OCT | D306: PURCHASE | F306: SAMVARDHANA MOTHER | G306: RTGS/SAMVAEDHANA /TMBLR52025100300610248 (Ref# 1544155) | H306: 13.34845 | I306: 0 | J306: 359030.4
A307: 306 | B307: 45934 | C307: OCT | D307: SALES | F307: METAL AND SC | G307: NEFT/METAL AND SCRAP TR/HDFCH00523318694 | H307: 0 | I307: 0.5138 | J307: 410410.4
A308: 307 | B308: 45934 | C308: OCT | D308: SALES | F308: MTC BUSINESS | G308: RTGS/MTC BUSINESS/HDFCR52025100468266197 | H308: 0 | I308: 4.58977 | J308: 869387.4
A309: 308 | B309: 45936 | C309: OCT | D309: SALES | F309: SRI AMBAL TRADE | G309: IMPS/SRI AMBAL TRADE/527911772406/ICIC/AFFANMETAL | H309: 0 | I309: 3 | J309: 1169387.4
A310: 309 | B310: 45936 | C310: OCT | D310: SIS CON | F310: VEERA INDUSTRIES-TMB-0123-OD | G310: TR/CHEPA/VEERA INDUSTRIES | H310: 0 | I310: 1.5 | J310: 1319387.4
A311: 310 | B311: 45936 | C311: OCT | D311: PURCHASE | F311: SAMVARDHANA MOTHER | G311: RTGS/SAMVARDHANA /TMBLR52025100600943408 (Ref# 1544157) | H311: 10 | I311: 0 | J311: 319387.4
...

Sheet PIVOT-TMB-0123-OD
B1: VEERA INDUSTRIES TMB-0123-OD(4.03 CR)
A4: ANALYSED BY : AKHILA(3.20PM-3.50PM)
C5: MONTH | D5: Values
C6: AUG | E6: SEP | G6: OCT | I6: NOV | K6: DEC | M6: JAN | O6: (blank) | Q6: Total Sum of DR | R6: Total Sum of CR
A7: TYPE | B7: Category | C7: Sum of DR | D7: Sum of CR | E7: Sum of DR | F7: Sum of CR | G7: Sum of DR | H7: Sum of CR | I7: Sum of DR | J7: Sum of CR | K7: Sum of DR | L7: Sum of CR | M7: Sum of DR | N7: Sum of CR | O7: Sum of DR | P7: Sum of CR
A8: CASH | B8: CASH WITHDRAWAL | C8: 2 | D8: 0 | E8: 4 | F8: 0 | G8: 2.5 | H8: 0 | I8: 1.5 | J8: 0 | K8: 5.5 | L8: 0 | Q8: 15.5 | R8: 0
A9: CASH Total | C9: 2 | D9: 0 | E9: 4 | F9: 0 | G9: 2.5 | H9: 0 | I9: 1.5 | J9: 0 | K9: 5.5 | L9: 0 | Q9: 15.5 | R9: 0
A10: SIS CON | B10: AFFAN METALS-TMB-5048-CA | C10: 107.1 | D10: 96.7 | E10: 37.5 | F10: 56 | G10: 46.2 | H10: 4.3 | I10: 110.2 | J10: 28.85 | K10: 52 | L10: 7.5 | M10: 63 | N10: 35 | Q10: 416 | R10: 228.35
A11: SIS CON Total | C11: 107.1 | D11: 96.7 | E11: 37.5 | F11: 56 | G11: 46.2 | H11: 4.3 | I11: 110.2 | J11: 28.85 | K11: 52 | L11: 7.5 | M11: 63 | N11: 35 | Q11: 416 | R11: 228.35
A12: UNMATCH SIS CON | B12: VEERA PROPERTIES | C12: 278.5 | D12: 0 | E12: 142 | F12: 7 | G12: 4.3 | H12: 0 | I12: 19.6 | J12: 6.3 | K12: 3.6 | L12: 7 | M12: 22 | N12: 0 | Q12: 470 | R12: 20.3
A13: UNMATCH SIS CON Total | C13: 278.5 | D13: 0 | E13: 142 | F13: 7 | G13: 4.3 | H13: 0 | I13: 19.6 | J13: 6.3 | K13: 3.6 | L13: 7 | M13: 22 | N13: 0 | Q13: 470 | R13: 20.3
A14: DOUBT | B14: Bill Id | C14: 0.476233 | D14: 30.32523 | E14: 0.1330792 | F14: 10.4948 | G14: 0.57228 | H14: 38.53556 | I14: 0.33318 | J14: 21.99366 | M14: 0.61295 | N14: 45.25767 | Q14: 2.1277222 | R14: 146.60692
B15: eBank | G15: 0.75 | H15: 0 | Q15: 0.75 | R15: 0
B16: TIN | E16: 1.51857 | F16: 0 | G16: 0.57162 | H16: 0 | I16: 1.26467 | J16: 0 | K16: 1.33636 | L16: 0 | M16: 1.23663 | N16: 0 | Q16: 5.92785 | R16: 0
A17: DOUBT Total | C17: 0.476233 | D17: 30.32523 | E17: 1.6516492 | F17: 10.4948 | G17: 1.8939 | H17: 38.53556 | I17: 1.59785 | J17: 21.99366 | K17: 1.33636 | L17: 0 | M17: 1.84958 | N17: 45.25767 | Q17: 8.8055722 | R17: 146.60692
A18: BANK FIN | B18: Interest Charges | C18: 3.36463 | D18: 0 | E18: 3.16422 | F18: 0 | G18: 3.27291 | H18: 0 | I18: 3.16471 | J18: 0 | K18: 3.27926 | L18: 0 | Q18: 16.24573 | R18: 0
A19: BANK FIN Total | C19: 3.36463 | D19: 0 | E19: 3.16422 | F19: 0 | G19: 3.27291 | H19: 0 | I19: 3.16471 | J19: 0 | K19: 3.27926 | L19: 0 | Q19: 16.24573 | R19: 0
A20: PVT FIN | B20: ADIMOOLAM N | C20: 0 | D20: 144 | M20: 80 | N20: 0 | Q20: 80 | R20: 144
B21: BARATHKUMAR | K21: 0 | L21: 9.9 | Q21: 0 | R21: 9.9
B22: CROWN TRADER | C22: 12.5 | D22: 0 | Q22: 12.5 | R22: 0
B23: GLOBAL ENTERPRISE | I23: 25 | J23: 0 | K23: 25 | L23: 0 | M23: 25 | N23: 0 | Q23: 75 | R23: 0
B24: GUNA S | C24: 0 | D24: 36 | Q24: 0 | R24: 36
B25: ROYAL AGENCY | C25: 12.5 | D25: 0 | Q25: 12.5 | R25: 0
A26: PVT FIN Total | C26: 25 | D26: 180 | I26: 25 | J26: 0 | K26: 25 | L26: 9.9 | M26: 105 | N26: 0 | Q26: 180 | R26: 189.9
A27: RETURN | B27: I/W CHQ RTN CHG | C27: 0.04425 | D27: 0 | I27: 0.04425 | J27: 0 | K27: 0.04425 | L27: 0 | Q27: 0.13275 | R27: 0
A28: RETURN Total | C28: 0.04425 | D28: 0 | I28: 0.04425 | J28: 0 | K28: 0.04425 | L28: 0 | Q28: 0.13275 | R28: 0
A29: Insurance | B29: Insurance | E29: 0.42483 | F29: 0 | I29: 0.34026 | J29: 0 | Q29: 0.76509 | R29: 0
A30: Insurance Total | E30: 0.42483 | F30: 0 | I30: 0.34026 | J30: 0 | Q30: 0.76509 | R30: 0
A31: EXPENSE | B31: Bank Charges | C31: 0.00885 | D31: 0 | E31: 0.00236 | F31: 0 | G31: 0.03357 | H31: 0 | I31: 0.00306 | J31: 0 | K31: 0.03211 | L31: 0 | Q31: 0.07995 | R31: 0
B32: EB BILL | C32: 0.5518054 | D32: 0 | G32: 0.8294154 | H32: 0 | I32: 0.5330354 | J32: 0 | Q32: 1.9142562 | R32: 0
B33: Penal Charges | E33: 0.00018 | F33: 0 | G33: 0.02167 | H33: 0 | K33: 0.00052 | L33: 0 | Q33: 0.02237 | R33: 0
B34: Salary Paid | C34: 0.22 | D34: 0 | E34: 0.25 | F34: 0 | G34: 0.23334 | H34: 0 | K34: 0.25 | L34: 0 | M34: 0.25 | N34: 0 | Q34: 1.20334 | R34: 0
B35: Tax | C35: 3.43467 | D35: 0 | E35: 1.54906 | F35: 0 | G35: 1.44442 | H35: 0 | I35: 3.86554 | J35: 0 | K35: 4.55896 | L35: 0 | M35: 1.6468 | N35: 0 | Q35: 16.49945 | R35: 0
B36: Utilities | I36: 0.0405158 | J36: 0 | Q36: 0.0405158 | R36: 0
A37: EXPENSE Total | C37: 4.2153254 | D37: 0 | E37: 1.8016 | F37: 0 | G37: 2.5624154 | H37: 0 | I37: 4.4421512 | J37: 0 | K37: 4.84159 | L37: 0 | M37: 1.8968 | N37: 0 | Q37: 19.759882 | R37: 0
A38: PURCHASE | B38: AARUPADAI CORPORAT | M38: 0.585 | N38: 0 | Q38: 0.585 | R38: 0
B39: ACHARYA STEE | I39: 10 | J39: 0 | K39: 18 | L39: 0 | M39: 23 | N39: 0 | Q39: 51 | R39: 0
B40: ANAND THAINESH | C40: 0.45 | D40: 0 | E40: 0.45 | F40: 0 | G40: 0.45 | H40: 0 | I40: 0.45 | J40: 0 | K40: 0.45 | L40: 0 | M40: 0.3629 | N40: 0 | Q40: 2.6129 | R40: 0
B41: AROKIYA TRAD | E41: 3.46 | F41: 0 | Q41: 3.46 | R41: 0
B42: BARRANQUESA INDIA | I42: 22 | J42: 0 | Q42: 22 | R42: 0
B43: COMPANY NAME | C43: 0.3367754 | D43: 0 | E43: 0.0360767 | F43: 0 | I43: 0.0267904 | J43: 0 | K43: 0.378 | L43: 0 | M43: 0.0282354 | N43: 0 | Q43: 0.8058779 | R43: 0
B44: D J ARCHITECTS | C44: 2 | D44: 0 | Q44: 2 | R44: 0
B45: DAYANA SUNDARA GLA | M45: 1 | N45: 0 | Q45: 1 | R45: 0
B46: JAGAN DURAI | C46: 1.2 | D46: 0 | E46: 0.2 | F46: 0 | G46: 0.2 | H46: 0 | I46: 0.15 | J46: 0 | K46: 0.15 | L46: 0 | M46: 0.2 | N46: 0 | Q46: 2.1 | R46: 0
B47: JUBILENT MOTORWORK | C47: 1.15534 | D47: 0 | Q47: 1.15534 | R47: 0
B48: K PANDURANGAN AND VA | I48: 0.36504 | J48: 0 | K48: 0.53908 | L48: 0 | Q48: 0.90412 | R48: 0
B49: K S S ENTERPRISES | I49: 20 | J49: 0 | Q49: 20 | R49: 0
B50: MOHANDOSS PARAMASI | C50: 0.12 | D50: 0 | E50: 0.16298 | F50: 0 | G50: 0.12 | H50: 0 | I50: 0.17 | J50: 0 | K50: 0.12 | L50: 0 | Q50: 0.69298 | R50: 0
B51: NAMASIVAYAM M | C51: 5.85548 | D51: 0 | K51: 8.92336 | L51: 0 | M51: 2.74821 | N51: 0 | Q51: 17.52705 | R51: 0
B52: OM ENTERPRIS | E52: 3.776 | F52: 0 | Q52: 3.776 | R52: 0
B53: PANDURANGAN | C53: 0.15844 | D53: 0 | G53: 0.18784 | H53: 0 | M53: 0.57852 | N53: 0 | Q53: 0.9248 | R53: 0
B54: PANKAJ ACHARYA | E54: 0.8 | F54: 0 | G54: 0.56 | H54: 0 | M54: 0.6 | N54: 0 | Q54: 1.96 | R54: 0
B55: PUNITHA G | C55: 5.71417 | D55: 0 | I55: 6.07616 | J55: 0 | M55: 5.3525 | N55: 0 | Q55: 17.14283 | R55: 0
B56: RAJASEKARAN RAVICHANDRAN | C56: 0.62 | D56: 0 | E56: 0.7643775 | F56: 0 | G56: 0.10304 | H56: 0 | I56: 0.25 | J56: 0 | K56: 0.55 | L56: 0 | M56: 0.55 | N56: 0 | Q56: 2.8374175 | R56: 0
B57: RAM NARAYAN | C57: 1.975 | D57: 0 | E57: 1.43 | F57: 0 | Q57: 3.405 | R57: 0
B58: S R RATHINAM | E58: 0.7015 | F58: 0 | Q58: 0.7015 | R58: 0
B59: S S S TRADER | E59: 5.55743 | F59: 0 | Q59: 5.55743 | R59: 0
B60: SELVAM V | C60: 1.23 | D60: 0 | E60: 1.73 | F60: 0 | G60: 3.23 | H60: 0 | I60: 1.23 | J60: 0 | Q60: 7.42 | R60: 0
B61: SRI AMBAL TRADE | C61: 10.35898 | D61: 0 | Q61: 10.35898 | R61: 0
B62: SRI PACHAIYAMMAN B | E62: 0.85 | F62: 0 | Q62: 0.85 | R62: 0
B63: SUNDARA PRABHU S | M63: 1 | N63: 0 | Q63: 1 | R63: 0
B64: THE KCP LTD | C64: 0.8717 | D64: 0 | E64: 0.17818 | F64: 0 | I64: 0.30974 | J64: 0 | Q64: 1.35962 | R64: 0
B65: VENUS INFRA | C65: 5.60529 | D65: 0 | Q65: 5.60529 | R65: 0
B66: VINOD KUMAR C | K66: 1 | L66: 0 | Q66: 1 | R66: 0
A67: PURCHASE Total | C67: 37.651175 | D67: 0 | E67: 20.096544 | F67: 0 | G67: 4.85088 | H67: 0 | I67: 61.02773 | J67: 0 | K67: 30.11044 | L67: 0 | M67: 36.005365 | N67: 0 | Q67: 189.74214 | R67: 0
A68: SALES | B68: ACHARYA STEE | C68: 0 | D68: 123 | E68: 0 | F68: 130 | G68: 0 | H68: 10 | I68: 0 | J68: 73 | K68: 0 | L68: 87.7 | M68: 0 | N68: 130 | Q68: 0 | R68: 553.7
B69: CASH DEPOSIT | I69: 0 | J69: 5 | K69: 0 | L69: 3.5 | Q69: 0 | R69: 8.5
B70: COMPANY NAME | G70: 0 | H70: 0.0006138 | K70: 0 | L70: 1e-05 | Q70: 0 | R70: 0.0006238
B71: K S S ENTERPRISES | I71: 0 | J71: 10 | Q71: 0 | R71: 10
B72: MEGHA STEELS | I72: 0 | J72: 29 | K72: 0 | L72: 10 | M72: 0 | N72: 23 | Q72: 0 | R72: 62
B73: S B METALS | C73: 0 | D73: 13.79267 | Q73: 0 | R73: 13.79267
B74: S M STEEL AL | C74: 0 | D74: 13.75 | E74: 0 | F74: 10 | G74: 0 | H74: 29.5 | I74: 0 | J74: 26.5 | Q74: 0 | R74: 79.75
B75: SRI AMBAL TRADE | I75: 0 | J75: 6.13174 | Q75: 0 | R75: 6.13174
B76: STAR INDUSTRI | E76: 0 | F76: 0.73594 | Q76: 0 | R76: 0.73594
A77: SALES Total | C77: 0 | D77: 150.54267 | E77: 0 | F77: 140.73594 | G77: 0 | H77: 39.500614 | I77: 0 | J77: 149.63174 | K77: 0 | L77: 101.20001 | M77: 0 | N77: 153 | Q77: 0 | R77: 734.61097
A78: (blank) | B78: (blank)
A79: (blank) Total
A80: Grand Total | C80: 458.35161 | D80: 457.5679 | E80: 210.63884 | F80: 214.23074 | G80: 65.580105 | H80: 82.336174 | I80: 226.91695 | J80: 206.7754 | K80: 125.7119 | L80: 125.60001 | M80: 229.75175 | N80: 233.25767 | Q80: 1316.9512 | R80: 1319.7679

Sheet XNS-TMB-0123-OD
A1: Sl. No. | B1: Date | C1: MONTH | D1: TYPE | E1: Cheque_No | F1: Category | G1: Description | H1: DR | I1: CR | J1: Balance
A2: 1 | B2: 45870 | C2: AUG | D2: SIS CON | F2: AFFAN METALS-TMB-5048-CA | G2: TR/CHEPA/AFFAN METALS | H2: 0 | I2: 2.95 | J2: -39962137
A3: 2 | B3: 45870 | C3: AUG | D3: DOUBT | F3: Bill Id | G3: Bill Id:[210DBP2600010]:PURCHASE | H3: 0 | I3: 19.1098 | J3: -38051157
A4: 3 | B4: 45870 | C4: AUG | D4: DOUBT | F4: Bill Id | G4: Bill Id:[210DBP2600010]:Interest Income A/c | H4: 0.300475 | I4: 0 | J4: -38081204
A5: 4 | B5: 45870 | C5: AUG | D5: EXPENSE | F5: Bank Charges | G5: TO/CHQ BOOK ISSUE CHARGES | H5: 0.00885 | I5: 0 | J5: -38082089
A6: 5 | B6: 45870 | C6: AUG | D6: PURCHASE | F6: THE KCP LTD | G6: NEFT/THE KCP LTD/TMBLH25213479485 (Ref# 1524746) | H6: 0.53942 | I6: 0 | J6: -38136031
A7: 6 | B7: 45870 | C7: AUG | D7: SIS CON | F7: AFFAN METALS-TMB-5048-CA | G7: TR/CHEPA/AFFAN METALS (Ref# 1524745) | H7: 18 | I7: 0 | J7: -39936031
A8: 7 | B8: 45871 | C8: AUG | D8: SIS CON | F8: AFFAN METALS-TMB-5048-CA | G8: TR/CHEPA/AFFAN METALS (Ref# 1524748) | H8: 0.1 | I8: 0 | J8: -39946031
A9: 8 | B9: 45871 | C9: AUG | D9: SALES | F9: ACHARYA STEE | G9: RTGS/ACHARYA STEE/HDFCR52025080297215695 | H9: 0 | I9: 50 | J9: -34946031
A10: 9 | B10: 45871 | C10: AUG | D10: PURCHASE | F10: MOHANDOSS PARAMASI | G10: NEFT/MOHANDOSS PARAMASI/TMBLH25214604509 (Ref# 1524747) | H10: 0.12 | I10: 0 | J10: -34958031
A11: 10 | B11: 45873 | C11: AUG | D11: SIS CON | F11: AFFAN METALS-TMB-5048-CA | G11: TR/CHEPA/AFFAN METALS (Ref# 1524749) | H11: 42 | I11: 0 | J11: -39158031
A12: 11 | B12: 45873 | C12: AUG | D12: SALES | F12: ACHARYA STEE | G12: RTGS/ACHARYA STEE/HDFCR52025080497334713 | H12: 0 | I12: 60 | J12: -33158031
A13: 12 | B13: 45873 | C13: AUG | D13: PURCHASE | F13: RAM NARAYAN | G13: NEFT/RAM NARAYAN/TMBLH25216779383 (Ref# 1524750) | H13: 0.135 | I13: 0 | J13: -33171531
... A19: 18 | B19: 45874 | C19: AUG | D19: EXPENSE | F19: Salary Paid | G19: eBank/Tr To RAJASEKARAN RAVICHANDRAN / SALARY | H19: 0.22 | I19: 0 | J19: -36474060
A20: 19 | B20: 45874 | C20: AUG | D20: PURCHASE | F20: ANAND THAINESH | G20: NEFT/ANAND T/TMBLH25217913218 | H20: 0.45 | I20: 0 | J20: -36519060 | L20: 100000
A21: 20 | B21: 45874 | C21: AUG | D21: UNMATCH SIS CON | F21: VEERA PROPERTIES | G21: TR/CHEPA/VEERA PROPERTIES (Ref# 1541764) | H21: 25 | I21: 0 | J21: -39019060
A22: 21 | B22: 45874 | C22: AUG | D22: PURCHASE | F22: COMPANY NAME | G22: TR/CHEPA/DEVARAJU RAJAMANIKKAM (Ref# 1541763) | H22: 0.3 | I22: 0 | J22: -39049060
A23: 22 | B23: 45874 | C23: AUG | D23: PURCHASE | F23: JUBILENT MOTORWORK | G23: NEFT/JUBILENT MOTORWORK/TMBLH25217917368 (Ref# 1541765) | H23: 1.15534 | I23: 0 | J23: -39164594
A24: 23 | B24: 45874 | C24: AUG | D24: EXPENSE | F24: EB BILL | G24: eBank/613284101/FACTORY EB BILL | H24: 0.5518054 | I24: 0 | J24: -39219775
A25: 24 | B25: 45874 | C25: AUG | D25: PURCHASE | F25: COMPANY NAME | G25: eBank/613284551/R.A PURAM EB | H25: 0.0367754 | I25: 0 | J25: -39223452
A26: 25 | B26: 45874 | C26: AUG | D26: SIS CON | F26: AFFAN METALS-TMB-5048-CA | G26: TR/CHEPA/AFFAN METALS | H26: 0 | I26: 18 | J26: -37423452
A27: 26 | B27: 45874 | C27: AUG | D27: UNMATCH SIS CON | F27: VEERA PROPERTIES | G27: TR/CHEPA/VEERA PROPERTIES (Ref# 1541766) | H27: 25 | I27: 0 | J27: -39923452
A28: 27 | B28: 45875 | C28: AUG | D28: SIS CON | F28: AFFAN METALS-TMB-5048-CA | G28: eBank/Tr From AFFAN METALS / TRANSFER TO VEERA | H28: 0 | I28: 25 | J28: -37423452
A29: 28 | B29: 45875 | C29: AUG | D29: UNMATCH SIS CON | F29: VEERA PROPERTIES | G29: eBank/Tr To VEERA PROPERTIES / VEERA P | H29: 25 | I29: 0 | J29: -39923452
A30: 29 | B30: 45875 | C30: AUG | D30: SIS CON | F30: AFFAN METALS-TMB-5048-CA | G30: eBank/Tr From AFFAN METALS / TRANSFER TO VEERA | H30: 0 | I30: 3 | J30: -39623452
A31: 30 | B31: 45875 | C31: AUG | D31: EXPENSE | F31: Tax | G31: eBank/CBDT/25080600697409 | H31: 1.32515 | I31: 0 | J31: -39755967
A32: 31 | B32: 45875 | C32: AUG | D32: EXPENSE | F32: Tax | G32: eBank/CBDT/25080600701516 | H32: 0.00952 | I32: 0 | J32: -39756919
... A377: 376 | B377: 46041 | C377: JAN | D377: PURCHASE | F377: RAJASEKARAN RAVICHANDRAN | G377: eBank/Tr To RAJASEKARAN RAVICHANDRAN | H377: 0.05 | I377: 0 | J377: -39975463

Sheet CONS
D2: AFFAN METALS & VEERA INDUSTRIES - 2 ACC PURCHASE &SALES
D5: MONTH | E5: AFFAN METALS TMB-5048-CA PURCHASE | F5: VEERA INDUSTRIES TMB-0123-OD PURCHASE | G5: PURCHASE TOTAL | H5: AFFAN METALS TMB-5048-CA SALES | I5: VEERA INDUSTRIES TMB-0123-OD SALES | J5: SALES TOTAL
D7: AUG | E7: =GETPIVOTDATA("Sum of DR",'PIVOT-TMB-5048-CA'!$A$6,"MONTH","AUG","TYPE","PURCHASE") -> 356.2274 | F7: =GETPIVOTDATA("Sum of DR",'PIVOT-TMB-0123-OD'!$A$5,"MONTH","AUG","TYPE","PURCHASE") -> 37.651175 | G7: =SUM(E7:F7) -> 393.87857 | H7: =GETPIVOTDATA("Sum of CR",'PIVOT-TMB-5048-CA'!$A$6,"MONTH","AUG","TYPE","SALES") -> 263.14775 | I7: =GETPIVOTDATA("Sum of CR",'PIVOT-TMB-0123-OD'!$A$5,"MONTH","AUG","TYPE","SALES") -> 150.54267 | J7: =SUM(H7:I7) -> 413.69042
D9: SEP | E9: =GETPIVOTDATA("Sum of DR",'PIVOT-TMB-5048-CA'!$A$6,"MONTH","SEP","TYPE","PURCHASE") -> 393.78004 | F9: =GETPIVOTDATA("Sum of DR",'PIVOT-TMB-0123-OD'!$A$5,"MONTH","SEP","TYPE","PURCHASE") -> 20.096544 | G9: =SUM(E9:F9) -> 413.87659 | H9: =GETPIVOTDATA("Sum of CR",'PIVOT-TMB-5048-CA'!$A$6,"MONTH","SEP","TYPE","SALES") -> 350.70611 | I9: =GETPIVOTDATA("Sum of CR",'PIVOT-TMB-0123-OD'!$A$5,"MONTH","SEP","TYPE","SALES") -> 140.73594 | J9: =SUM(H9:I9) -> 491.44205
D11: OCT | E11: =GETPIVOTDATA("Sum of DR",'PIVOT-TMB-5048-CA'!$A$6,"MONTH","OCT","TYPE","PURCHASE") -> 309.54648 | F11: =GETPIVOTDATA("Sum of DR",'PIVOT-TMB-0123-OD'!$A$5,"MONTH","OCT","TYPE","PURCHASE") -> 4.85088 | G11: =SUM(E11:F11) -> 314.39736 | H11: =GETPIVOTDATA("Sum of CR",'PIVOT-TMB-5048-CA'!$A$6,"MONTH","OCT","TYPE","SALES") -> 276.61912 | I11: =GETPIVOTDATA("Sum of CR",'PIVOT-TMB-0123-OD'!$A$5,"MONTH","OCT","TYPE","SALES") -> 39.500614 | J11: =SUM(H11:I11) -> 316.11973
D13: NOV | E13: =GETPIVOTDATA("Sum of DR",'PIVOT-TMB-5048-CA'!$A$6,"MONTH","NOV","TYPE","PURCHASE") -> 367.1384 | F13: =GETPIVOTDATA("Sum of DR",'PIVOT-TMB-0123-OD'!$A$5,"MONTH","NOV","TYPE","PURCHASE") -> 61.02773 | G13: =SUM(E13:F13) -> 428.16613 | H13: =GETPIVOTDATA("Sum of CR",'PIVOT-TMB-5048-CA'!$A$6,"MONTH","NOV","TYPE","SALES") -> 305.08931 | I13: =GETPIVOTDATA("Sum of CR",'PIVOT-TMB-0123-OD'!$A$5,"MONTH","NOV","TYPE","SALES") -> 149.63174 | J13: =SUM(H13:I13) -> 454.72105
D15: DEC | E15: =GETPIVOTDATA("Sum of DR",'PIVOT-TMB-5048-CA'!$A$6,"MONTH","DEC","TYPE","PURCHASE") -> 319.31888 | F15: =GETPIVOTDATA("Sum of DR",'PIVOT-TMB-0123-OD'!$A$5,"MONTH","DEC","TYPE","PURCHASE") -> 30.11044 | G15: =SUM(E15:F15) -> 349.42932 | H15: =GETPIVOTDATA("Sum of CR",'PIVOT-TMB-5048-CA'!$A$6,"MONTH","DEC","TYPE","SALES") -> 277.86643 | I15: =GETPIVOTDATA("Sum of CR",'PIVOT-TMB-0123-OD'!$A$5,"MONTH","DEC","TYPE","SALES") -> 101.20001 | J15: =SUM(H15:I15) -> 379.06644
D17: JAN (26) | E17: =GETPIVOTDATA("Sum of DR",'PIVOT-TMB-5048-CA'!$A$6,"MONTH","JAN(26)","TYPE","PURCHASE") -> 142.5993 | F17: =GETPIVOTDATA("Sum of DR",'PIVOT-TMB-0123-OD'!$A$5,"MONTH","JAN","TYPE","PURCHASE") -> 36.005365 | G17: =SUM(E17:F17) -> 178.60467 | H17: =GETPIVOTDATA("Sum of CR",'PIVOT-TMB-5048-CA'!$A$6,"MONTH","JAN(26)","TYPE","SALES") -> 109.39409 | I17: =GETPIVOTDATA("Sum of CR",'PIVOT-TMB-0123-OD'!$A$5,"MONTH","JAN","TYPE","SALES") -> 153 | J17: =SUM(H17:I17) -> 262.39409
E19: TOTAL PURCHASE | G19: =SUM(G6:G18) -> 2078.3526 | H19: TOTAL SALES | J19: =SUM(J6:J18) -> 2317.4338

Sheet FINAL
G14: INWARD CHEQUE RETURN | H14: YES
G15: ECS CHEQUE RETURN | H15: YES
G16: IRREUGULAR REPAYMENT FINANCE | H16: YES
G17: PRIVATE FINANCE ON DATE | H17: NO
G18: PRIVATE FINANCE 10% | H18: YES
G19: BANK FINANCE 10% | H19: YES
G20: GSTR RECEIVED | H20: NO
G21: TURN OVER (MONTHLY) INCREASE / DECREASE | H21: INCREASE
G22: Is there any other bank statement? – NEED STATEMENT
G23: OUR FEED BACK
